[{"id":"41652030","name":"Carroll Health Group LLC","telephone":"(410) 861-8960","address":"2970 Dede Rd #4 Finksburg, MD 21048","properties1":["Neurology"],"properties2":[],"properties3":[]},{"id":"57011087","name":"Mathew, Abraham, MD","telephone":"(410) 833-3063","address":"3125 Baltimore Blvd Finksburg, MD 21048","properties1":["Family Practice","Years in Practice: 19"],"properties2":["American Board of Medical Specialties","Evidence Based Medicine Standards"],"properties3":[]},{"id":"69757583","name":"Charter Radiology LLC","telephone":"(443) 917-2855","address":"116 Westminster Pike #104 Reisterstown, MD 21136","properties1":["Radiology, Diagnostic"],"properties2":[],"properties3":[]},{"id":"32808621","name":"Koman, Jon D, MD","telephone":"(410) 833-9300","address":"116 Westminster Pike #100 Reisterstown, MD 21136","properties1":["Orthopedic Surgery - Board Certified","Years in Practice: 23"],"properties2":["American Board of Medical Specialties","\n\t\t\t\t\t\t\t\t\t\t\t\t\tNot enough info to evaluate for Evidence Based Medicine Standards.\n\t\t\t\t\t\t\t\t\t\t\t\t"],"properties3":[]},{"id":"40765722","name":"Koman Orthopaedics &amp; Sports Medicine LLC","telephone":"(410) 833-9300","address":"116 Westminster Pike #100 Reisterstown, MD 21136","properties1":["Physical Therapy"],"properties2":[],"properties3":[]}]
