[{"id":"32915526","name":"Soukup-Taylor, Elizabeth, MA, LCSW","telephone":"(703) 396-8618","address":"2701 Hunter Pl #201 Woodbridge, VA 22193","properties1":["Social Work"],"properties2":[],"properties3":[]},{"id":"57909491","name":"Hobbs, Karen R, MA, LPC","telephone":"(703) 772-2023","address":"4408 Echo Ct Woodbridge, VA 22193","properties1":["Counseling - Board Certified","Social Work - Board Certified"],"properties2":["American Board of Medical Specialties"],"properties3":[]},{"id":"35745404","name":"Gohel, Shailesh K, MD","telephone":"(703) 670-0300","address":"4201 Dale Blvd Dale City, VA 22193","properties1":["Pediatrics - Board Certified","Years in Practice: 16"],"properties2":["American Board of Medical Specialties","Evidence Based Medicine Standards"],"properties3":[]},{"id":"64659475","name":"Boulevard Center Pediatrics, Inc","telephone":"(703) 670-0300","address":"4201 Dale Blvd Dale City, VA 22193","properties1":["Pediatrics"],"properties2":[],"properties3":[]},{"id":"51626360","name":"Kancir-Azer, Ljubica M, MD","telephone":"(703) 680-5959","address":"4158 Dale Blvd Dale City, VA 22193","properties1":["Internal Medicine","Years in Practice: 55"],"properties2":["American Board of Medical Specialties"],"properties3":[]},{"id":"59188714","name":"Alidoost, Nosrat A, MD","telephone":"(703) 680-5959","address":"4158 Dale Blvd Dale City, VA 22193","properties1":["Internal Medicine","Years in Practice: 45"],"properties2":["American Board of Medical Specialties"],"properties3":[]},{"id":"29000483","name":"Salehi, Mina, MD","telephone":"(703) 680-5959","address":"4158 Dale Blvd Woodbridge, VA 22193","properties1":["Internal Medicine - Board Certified","Years in Practice: 26"],"properties2":["American Board of Medical Specialties"],"properties3":[]},{"id":"25158796","name":"Motameni, Neda, MD","telephone":"(703) 680-5959","address":"4158 Dale Blvd Woodbridge, VA 22193","properties1":["Internal Medicine - Board Certified","Years in Practice: 17"],"properties2":["American Board of Medical Specialties"],"properties3":[]},{"id":"64509281","name":"Dalewood Medical Enterprises, Inc","telephone":"(703) 680-5959","address":"4158 Dale Blvd Dale City, VA 22193","properties1":["Internal Medicine"],"properties2":[],"properties3":[]},{"id":"63496910","name":"Fagbenro, Carlos K, MSN","telephone":"(571) 594-9110","address":"4215 Dale Blvd Woodbridge, VA 22193","properties1":["Family Nurse Practitioner - Primary Care","Years in Practice: 6"],"properties2":["American Board of Medical Specialties"],"properties3":[]},{"id":"53016946","name":"Nzeogu, Ikenna S, DO","telephone":"(571) 351-1227","address":"4215 Dale Blvd Woodbridge, VA 22193","properties1":["Family Practice","Years in Practice: 21"],"properties2":["American Board of Medical Specialties","\n\t\t\t\t\t\t\t\t\t\t\t\t\tNot enough info to evaluate for Evidence Based Medicine Standards.\n\t\t\t\t\t\t\t\t\t\t\t\t"],"properties3":[]},{"id":"20687950","name":"Meiller, Roger A, DC","telephone":"(703) 897-8600","address":"4205 Dale Blvd Woodbridge, VA 22193","properties1":["Chiropractic"],"properties2":[],"properties3":[]},{"id":"44672127","name":"Levin, Arnold S, DPM","telephone":"(703) 670-9401","address":"4225 Dale Blvd Woodbridge, VA 22193","properties1":["Podiatry","Years in Practice: 42"],"properties2":[],"properties3":[]},{"id":"54032826","name":"Rodd, Sam C, MD","telephone":"(703) 670-2176","address":"4221 Dale Blvd Woodbridge, VA 22193","properties1":["Internal Medicine","Years in Practice: 37"],"properties2":["American Board of Medical Specialties","Evidence Based Medicine Standards"],"properties3":[]},{"id":"58839600","name":"Deola, Jerry J, MD, OD","telephone":"(703) 670-8085","address":"4460 Dale Blvd Dale City, VA 22193","properties1":["Optometry","Years in Practice: 41"],"properties2":[],"properties3":[]},{"id":"34796614","name":"Meza, Griselda M, MD","telephone":"(703) 580-6400","address":"14009 Minnieville Rd Woodbridge, VA 22193","properties1":["Pediatrics - Board Certified","Years in Practice: 10"],"properties2":["American Board of Medical Specialties"],"properties3":[]},{"id":"58703144","name":"Zweibahmer, Michele L, MS, LPC","telephone":"(703) 878-6670","address":"14377 Hereford Rd Woodbridge, VA 22193","properties1":["Counseling - Board Certified"],"properties2":["American Board of Medical Specialties"],"properties3":[]},{"id":"47562973","name":"Fullen, Megan M, MSW, LCSW","telephone":"(703) 878-6670","address":"14377 Hereford Rd Woodbridge, VA 22193","properties1":["Social Work - Board Certified"],"properties2":["American Board of Medical Specialties"],"properties3":[]},{"id":"33941849","name":"Odell, Tanya M, MS, LPC","telephone":"(703) 878-6670","address":"14377 Hereford Rd Woodbridge, VA 22193","properties1":["Counseling - Board Certified"],"properties2":["American Board of Medical Specialties"],"properties3":[]},{"id":"63701967","name":"Gill, Naurang S, MD, DO","telephone":"(703) 670-9553","address":"14401 Hereford Rd Woodbridge, VA 22193","properties1":["Neurology","Years in Practice: 43"],"properties2":["\n\t\t\t\t\t\t\t\t\t\t\t\t\tNot enough info to evaluate for Evidence Based Medicine Standards.\n\t\t\t\t\t\t\t\t\t\t\t\t"],"properties3":[]},{"id":"63050585","name":"Smith, Tara D, PHD, CP","telephone":"(703) 490-0336","address":"13885 Hedgewood Dr #245 Woodbridge, VA 22193","properties1":["Psychology - Board Certified"],"properties2":["American Board of Medical Specialties"],"properties3":[]},{"id":"62654170","name":"Hicks, Shakoya C, MA, LPC","telephone":"(703) 490-0336","address":"13885 Hedgewood Dr #245 Woodbridge, VA 22193","properties1":["Counseling"],"properties2":[],"properties3":[]},{"id":"47799394","name":"Schell-Smith, Michael D, MSW, LCSW","telephone":"(703) 490-0336","address":"13885 Hedgewood Dr #245 Woodbridge, VA 22193","properties1":["Social Work - Board Certified"],"properties2":["American Board of Medical Specialties"],"properties3":[]},{"id":"48326657","name":"Long, Susanne K, PHD, CP","telephone":"(703) 490-0336","address":"13885 Hedgewood Dr #245 Woodbridge, VA 22193","properties1":["Psychology - Board Certified"],"properties2":["American Board of Medical Specialties"],"properties3":[]},{"id":"63942426","name":"Alathari, Husam K, MD","telephone":"(703) 492-2924","address":"13885 Hedgewood Dr #349 Woodbridge, VA 22193","properties1":["Psychiatry - Board Certified"],"properties2":["American Board of Medical Specialties"],"properties3":[]},{"id":"54771338","name":"Weng, Jan A, PC, MA, LPC","telephone":"(703) 492-8939","address":"13885 Hedgewood Dr #349 Woodbridge, VA 22193","properties1":["Counseling - Board Certified"],"properties2":["American Board of Medical Specialties"],"properties3":[]},{"id":"31759184","name":"Hart-Johnson, Mary F, MSN, LNP","telephone":"(703) 492-2924","address":"13885 Hedgewood Dr #349 Woodbridge, VA 22193","properties1":["Counseling - Board Certified"],"properties2":["American Board of Medical Specialties"],"properties3":[]},{"id":"35352429","name":"Luedtke, Lindsey K, PSYD, LP, CPC, CP","telephone":"(703) 490-0336","address":"13885 Hedgewood Dr #245 Woodbridge, VA 22193","properties1":["Psychology - Board Certified"],"properties2":["American Board of Medical Specialties"],"properties3":[]},{"id":"37628879","name":"Broudy, Matthew S, PHD, LCP, CP","telephone":"(703) 490-0336","address":"13885 Hedgewood Dr #245 Woodbridge, VA 22193","properties1":["Psychology - Board Certified"],"properties2":["American Board of Medical Specialties"],"properties3":[]},{"id":"22336738","name":"Grimes, Dara M, MA, LCSW","telephone":"(703) 490-0336","address":"13885 Hedgewood Dr #245 Woodbridge, VA 22193","properties1":["Social Work - Board Certified"],"properties2":["American Board of Medical Specialties"],"properties3":[]},{"id":"22440201","name":"Leisersohn, Felicia J, PSYD, CP","telephone":"(703) 490-0336","address":"13885 Hedgewood Dr #245 Woodbridge, VA 22193","properties1":["Psychology - Board Certified"],"properties2":["American Board of Medical Specialties"],"properties3":[]},{"id":"29461457","name":"Batts, Ayonda E, PHD, CP","telephone":"(703) 490-0336","address":"13885 Hedgewood Dr #245 Woodbridge, VA 22193","properties1":["Psychology - Board Certified"],"properties2":["American Board of Medical Specialties"],"properties3":[]},{"id":"27985654","name":"Mansfield, Sandra M, MSW, LCSW","telephone":"(703) 490-0336","address":"13885 Hedgewood Dr #245 Woodbridge, VA 22193","properties1":["Social Work"],"properties2":[],"properties3":[]},{"id":"23513330","name":"Strand, Kimberly, PHD, CP","telephone":"(703) 490-0336","address":"13885 Hedgewood Dr #245 Woodbridge, VA 22193","properties1":["Psychology - Board Certified"],"properties2":["American Board of Medical Specialties"],"properties3":[]},{"id":"22860984","name":"Taylor-Pickford, Jessica R, MSW, LCSW","telephone":"(703) 490-0336","address":"13885 Hedgewood Dr #245 Woodbridge, VA 22193","properties1":["Social Work - Board Certified"],"properties2":["American Board of Medical Specialties"],"properties3":[]},{"id":"23106779","name":"Diaz-Garcia, Aidil, MA, LPC","telephone":"(703) 492-8939","address":"13885 Hedgewood Dr Woodbridge, VA 22193","properties1":["Counseling - Board Certified"],"properties2":["American Board of Medical Specialties"],"properties3":[]},{"id":"35375083","name":"Zander, Gail, PHD, LP, CP","telephone":"(703) 490-0336","address":"13885 Hedgewood Dr #245 Woodbridge, VA 22193","properties1":["Psychology - Board Certified"],"properties2":["American Board of Medical Specialties"],"properties3":[]},{"id":"30094892","name":"Borash, Michael H, MSED, LPC, CSAC","telephone":"(703) 492-7698","address":"13885 Hedgewood Dr #349 Woodbridge, VA 22193","properties1":["Counseling - Board Certified"],"properties2":["American Board of Medical Specialties"],"properties3":[]},{"id":"29275521","name":"Mazer, Alaina, MED, LPC","telephone":"(703) 490-0336","address":"13885 Hedgewood Dr #245 Woodbridge, VA 22193","properties1":["Counseling - Board Certified"],"properties2":["American Board of Medical Specialties"],"properties3":[]},{"id":"22670909","name":"Pernod Liboy, Nicole E, PSYD, CP","telephone":"(703) 490-0336","address":"13885 Hedgewood Dr #245 Woodbridge, VA 22193","properties1":["Psychology"],"properties2":[],"properties3":[]},{"id":"39806905","name":"Eid, Mark P, MD","telephone":"(540) 373-6647","address":"13875 Hedgewood Dr Woodbridge, VA 22193","properties1":["Dermatology - Board Certified","Years in Practice: 11"],"properties2":["American Board of Medical Specialties","\n\t\t\t\t\t\t\t\t\t\t\t\t\tNot enough info to evaluate for Evidence Based Medicine Standards.\n\t\t\t\t\t\t\t\t\t\t\t\t"],"properties3":[]},{"id":"54726716","name":"May, Jivan S, MSW, LCSW","telephone":"(540) 845-6940","address":"13895 Hedgewood Dr #307 Woodbridge, VA 22193","properties1":["Social Work - Board Certified"],"properties2":["American Board of Medical Specialties"],"properties3":[]},{"id":"39810703","name":"Epstein, Jason B, PSYD, CP","telephone":"(703) 389-1931","address":"13895 Hedgewood Dr #313 Woodbridge, VA 22193","properties1":["Psychology"],"properties2":[],"properties3":[]},{"id":"50054629","name":"Cook, Kimberly L, MSW, LCSWC","telephone":"(800) 491-5369","address":"13600 Minnieville Rd Woodbridge, VA 22193","properties1":["Social Work - Board Certified"],"properties2":["American Board of Medical Specialties"],"properties3":[]},{"id":"31732912","name":"Kuhns, Michael P, MS, LPC","telephone":"(800) 491-5369","address":"13600 Minnieville Rd Woodbridge, VA 22193","properties1":["Counseling - Board Certified"],"properties2":["American Board of Medical Specialties"],"properties3":[]},{"id":"50490916","name":"Sparg, Olivia, MA, LBA","telephone":"(703) 237-2219","address":"14130 Noblewood Plz #301 Woodbridge, VA 22193","properties1":["Counseling"],"properties2":[],"properties3":[]},{"id":"50613363","name":"Gauvin, Wali, MD","telephone":"(703) 485-0470","address":"14130 Noblewood Plz #306 Woodbridge, VA 22193","properties1":["Pediatric Cardiology - Board Certified","Years in Practice: 17"],"properties2":["American Board of Medical Specialties"],"properties3":[]},{"id":"49379624","name":"Casamalhuapa, Martha L, MD","telephone":"(703) 485-0470","address":"14130 Noblewood Plz #306 Woodbridge, VA 22193","properties1":["Pediatrics","Years in Practice: 12"],"properties2":["American Board of Medical Specialties","\n\t\t\t\t\t\t\t\t\t\t\t\t\tNot enough info to evaluate for Evidence Based Medicine Standards.\n\t\t\t\t\t\t\t\t\t\t\t\t"],"properties3":[]},{"id":"51647771","name":"Thome, Julia, BS, BCBA, BCABA","telephone":"(703) 237-2219","address":"14130 Noblewood Plz #301 Woodbridge, VA 22193","properties1":["Counseling - Board Certified"],"properties2":["American Board of Medical Specialties"],"properties3":[]},{"id":"36027689","name":"Ashfaq, Mohammad, OD","telephone":"(703) 878-2020","address":"14130 Noblewood Plz #105 Woodbridge, VA 22193","properties1":["Optometry"],"properties2":[],"properties3":[]},{"id":"36501610","name":"Tafere, Bethel Z, MS, LBA","telephone":"(703) 237-2219","address":"14130 Noblewood Plz #301 Woodbridge, VA 22193","properties1":["Counseling"],"properties2":[],"properties3":[]},{"id":"60868037","name":"Esmaeili, Pendar, DC","telephone":"(703) 897-7777","address":"3985 Prince William Pky #101 Woodbridge, VA 22192","properties1":["Chiropractic - Board Certified"],"properties2":["American Board of Medical Specialties"],"properties3":[]},{"id":"31420945","name":"Bhattarai, Prithvi, NP","telephone":"(703) 590-8375","address":"3985 Prince William Pky #102 Woodbridge, VA 22192","properties1":["Nurse Practitioner - Board Certified"],"properties2":["American Board of Medical Specialties"],"properties3":[]},{"id":"40299124","name":"Morgan, Ezra M, MD","telephone":"(703) 730-1735","address":"4001 Prince William Pky #201 Woodbridge, VA 22192","properties1":["Family Practice","Years in Practice: 23"],"properties2":["American Board of Medical Specialties","\n\t\t\t\t\t\t\t\t\t\t\t\t\tNot enough info to evaluate for Evidence Based Medicine Standards.\n\t\t\t\t\t\t\t\t\t\t\t\t"],"properties3":[]},{"id":"33707264","name":"Esmaeili, Nahal, DC","telephone":"(703) 897-7777","address":"3985 Prince William Pky #101 Woodbridge, VA 22192","properties1":["Chiropractic - Board Certified"],"properties2":["American Board of Medical Specialties"],"properties3":[]},{"id":"20056851","name":"Neberai, Salah M, MD","telephone":"(571) 402-7130","address":"4001 Prince William Pky #200 Woodbridge, VA 22192","properties1":["Pediatrics - Board Certified","Years in Practice: 32"],"properties2":["American Board of Medical Specialties","Evidence Based Medicine Standards"],"properties3":[]},{"id":"25512009","name":"Golesorkhi, Reza, MD","telephone":"(703) 590-8375","address":"3985 Prince William Pky #102 Woodbridge, VA 22192","properties1":["Family Practice","Years in Practice: 19"],"properties2":["American Board of Medical Specialties","Evidence Based Medicine Standards"],"properties3":[]},{"id":"40927402","name":"Best Health Services PC","telephone":"(703) 204-0355","address":"3985 Prince William Pky #106 Woodbridge, VA 22192","properties1":["Sleep Medicine"],"properties2":[],"properties3":[]},{"id":"39385759","name":"Yousefi, Meimanat B, DC","telephone":"(703) 730-9222","address":"3955 Prince William Pky Woodbridge, VA 22192","properties1":["Chiropractic - Board Certified"],"properties2":["American Board of Medical Specialties"],"properties3":[]},{"id":"47262872","name":"Ryu, Sang K, DC","telephone":"(703) 730-9222","address":"3945 Prince William Pky Woodbridge, VA 22192","properties1":["Chiropractic - Board Certified"],"properties2":["American Board of Medical Specialties"],"properties3":[]},{"id":"26607026","name":"Yousefi, Mohammad, DC","telephone":"(703) 730-9222","address":"3945 Prince William Pky Woodbridge, VA 22192","properties1":["Chiropractic - Board Certified"],"properties2":["American Board of Medical Specialties"],"properties3":[]},{"id":"51988499","name":"Hunt, Diana, FNP","telephone":"(571) 659-9387","address":"5808 Mapledale Plz Dale City, VA 22193","properties1":["Family Nurse Practitioner - Primary Care","Years in Practice: 2"],"properties2":["American Board of Medical Specialties"],"properties3":[]},{"id":"25592663","name":"Duong, Tuan Q, OD","telephone":"(703) 583-2020","address":"5884 Mapledale Plz Woodbridge, VA 22193","properties1":["Optometry"],"properties2":[],"properties3":[]},{"id":"64113647","name":"Easy Care Urgent Care","telephone":"(571) 659-9387","address":"5808 Mapledale Plz Dale City, VA 22193","properties1":["Family Nurse Practitioner - Primary Care"],"properties2":[],"properties3":[]},{"id":"64380177","name":"Active Chiropractic Clinic LLC","telephone":"(703) 680-3332","address":"5864 Mapledale Plz Woodbridge, VA 22193","properties1":["Chiropractic"],"properties2":[],"properties3":[]},{"id":"49325015","name":"Jalloh, Kadija, FNP, APRN","telephone":"(703) 730-2000","address":"13168 Centerpointe Way #101 Woodbridge, VA 22193","properties1":["Family Nurse Practitioner - Primary Care","Years in Practice: 2"],"properties2":["American Board of Medical Specialties"],"properties3":[]},{"id":"53925517","name":"Medimpudi, Aruna, MD, MBBS","telephone":"(703) 730-2000","address":"13168 Centerpointe Way #101 Woodbridge, VA 22193","properties1":["Family Practice - Board Certified"],"properties2":["NCQA's Patient-Centered Medical Home Recognition","American Board of Medical Specialties","Evidence Based Medicine Standards"],"properties3":[]},{"id":"57025854","name":"Vaddadi, Gayatri K, MD, MBBS","telephone":"(703) 730-2000","address":"13168 Centerpointe Way #101 Woodbridge, VA 22193","properties1":["Family Practice - Board Certified"],"properties2":["American Board of Medical Specialties","Evidence Based Medicine Standards"],"properties3":[]},{"id":"45007028","name":"Ghadge, Priya D, MD","telephone":"(703) 730-2000","address":"13168 Centerpointe Way #101 Woodbridge, VA 22193","properties1":["Family Practice - Board Certified"],"properties2":["NCQA's Patient-Centered Medical Home Recognition","American Board of Medical Specialties","Evidence Based Medicine Standards"],"properties3":[]},{"id":"47803965","name":"Simpson, Rickie T, PHD, CNS","telephone":"(703) 590-5999","address":"13168 Centerpointe Way #101 Woodbridge, VA 22193","properties1":["Behaviorial Nurse"],"properties2":[],"properties3":[]},{"id":"24763182","name":"Kopparti, Nirupama, MD, MBBS","telephone":"(703) 689-0111","address":"13168 Centerpointe Way #101 Woodbridge, VA 22193","properties1":["Family Practice - Board Certified","Years in Practice: 18"],"properties2":["American Board of Medical Specialties","Evidence Based Medicine Standards"],"properties3":[]},{"id":"36764351","name":"Patel, Sneha R, MD","telephone":"(703) 730-2000","address":"13168 Centerpointe Way #101 Woodbridge, VA 22193","properties1":["Family Practice - Board Certified","Years in Practice: 9"],"properties2":["American Board of Medical Specialties"],"properties3":[]},{"id":"32237748","name":"Bommasani, Reena R, MD","telephone":"(703) 730-2000","address":"13168 Centerpointe Way #101 Woodbridge, VA 22193","properties1":["Family Practice - Board Certified","Years in Practice: 22"],"properties2":["NCQA's Patient-Centered Medical Home Recognition","American Board of Medical Specialties","Evidence Based Medicine Standards"],"properties3":[]},{"id":"23220508","name":"Sanaei Ardekani, Mohammad S, MD","telephone":"(703) 361-7341","address":"14000 Crown Ct #110 Woodbridge, VA 22193","properties1":["Nephrology - Board Certified"],"properties2":["American Board of Medical Specialties"],"properties3":[]},{"id":"32924090","name":"Harar, Andrew, MED, LPC","telephone":"(703) 659-9900","address":"14000 Crown Ct #101 Woodbridge, VA 22193","properties1":["Counseling - Board Certified"],"properties2":["American Board of Medical Specialties"],"properties3":[]},{"id":"38279996","name":"Coleman, Christopher, MS, LPC","telephone":"(703) 659-9900","address":"14000 Crown Ct #101 Woodbridge, VA 22193","properties1":["Counseling - Board Certified"],"properties2":["American Board of Medical Specialties"],"properties3":[]},{"id":"33517940","name":"Lee, Llewellyn V, MD","telephone":"(703) 763-5224","address":"14085 Crown Ct Woodbridge, VA 22193","properties1":["Vascular and Interventional Radiology - Board Certified","Years in Practice: 16"],"properties2":["American Board of Medical Specialties"],"properties3":[]},{"id":"25111404","name":"Shah, Anish P, MD","telephone":"(703) 763-5224","address":"14085 Crown Ct Woodbridge, VA 22193","properties1":["Surgery, Vascular","Years in Practice: 14"],"properties2":["\n\t\t\t\t\t\t\t\t\t\t\t\t\tNot enough info to evaluate for Evidence Based Medicine Standards.\n\t\t\t\t\t\t\t\t\t\t\t\t"],"properties3":[]},{"id":"21152995","name":"Washer, Joshua D, MD","telephone":"(703) 763-5224","address":"14085 Crown Ct Woodbridge, VA 22193","properties1":["Surgery, General - Board Certified","Surgery, Vascular","Years in Practice: 10"],"properties2":["American Board of Medical Specialties","Evidence Based Medicine Standards"],"properties3":[]},{"id":"40670183","name":"Vascular Institute of Virginia LLC","telephone":"(703) 763-5224","address":"14085 Crown Ct Woodbridge, VA 22193","properties1":["Surgery, Vascular"],"properties2":[],"properties3":[]},{"id":"39783701","name":"Graves, Nancy J, OD","telephone":"(703) 590-2888","address":"3102 Golansky Blvd #101 Woodbridge, VA 22192","properties1":["Optometry","Years in Practice: 49"],"properties2":[],"properties3":[]},{"id":"60700275","name":"Wang, Richard K, MD, DMD","telephone":"(703) 897-8983","address":"3158 Golansky Blvd #102 Woodbridge, VA 22192","properties1":["Surgery, Oral And Maxillofacial - Board Certified","Years in Practice: 19"],"properties2":["American Board of Medical Specialties"],"properties3":[]},{"id":"25903069","name":"Pell, James A, DDS","telephone":"(703) 897-8983","address":"3158 Golansky Blvd #102 Woodbridge, VA 22192","properties1":["Surgery, Oral And Maxillofacial - Board Certified","Years in Practice: 41"],"properties2":["American Board of Medical Specialties"],"properties3":[]},{"id":"41332170","name":"Oral Surgery Associates","telephone":"(703) 897-8983","address":"3158 Golansky Blvd #102 Woodbridge, VA 22192","properties1":["Surgery, Oral And Maxillofacial"],"properties2":[],"properties3":[]},{"id":"63607388","name":"Bethea, Shantelle M, RD","telephone":"(703) 890-9842","address":"3622 Serendipity Rd Woodbridge, VA 22193","properties1":["Registered Dietician"],"properties2":[],"properties3":[]},{"id":"60451771","name":"Shah, Tejas J, MD","telephone":"(703) 580-0124","address":"4331 Ridgewood Center Dr Woodbridge, VA 22192","properties1":["Family Practice - Board Certified","Years in Practice: 24"],"properties2":["American Board of Medical Specialties","Evidence Based Medicine Standards"],"properties3":[]},{"id":"53114663","name":"Martinez, Carmen Y, PAC","telephone":"(703) 680-7950","address":"4379 Ridgewood Center Dr Woodbridge, VA 22192","properties1":["Physician Assistant"],"properties2":["NCQA's Patient-Centered Medical Home Recognition"],"properties3":[]},{"id":"54924761","name":"Moore, Maura M, MSW, LCSW","telephone":"(703) 897-8970","address":"4349 Ridgewood Center Dr #101 Woodbridge, VA 22192","properties1":["Social Work - Board Certified"],"properties2":["American Board of Medical Specialties"],"properties3":[]},{"id":"50609860","name":"Dwamena, Natasha A, MD","telephone":"(703) 680-7950","address":"4379 Ridgewood Center Dr #102 Woodbridge, VA 22192","properties1":["Obstetrics and Gynecology - Board Certified","Years in Practice: 12"],"properties2":["American Board of Medical Specialties"],"properties3":[]},{"id":"49824563","name":"Bindrim, Erica D, NP, MSN, LNP","telephone":"(703) 897-8970","address":"4349 Ridgewood Center Dr #101 Woodbridge, VA 22192","properties1":["Counseling - Board Certified","Behaviorial Nurse"],"properties2":["American Board of Medical Specialties"],"properties3":[]},{"id":"63849558","name":"Hibbert, Jill N, CNM","telephone":"(703) 680-7950","address":"4379 Ridgewood Center Dr #102 Woodbridge, VA 22192","properties1":["Midwife"],"properties2":[],"properties3":[]},{"id":"47400519","name":"Wiener, Lisa, MSN, CNM","telephone":"(703) 680-7950","address":"4379 Ridgewood Center Dr #102 Woodbridge, VA 22192","properties1":["Midwife","Years in Practice: 22"],"properties2":[],"properties3":[]},{"id":"46843791","name":"Marquez, Ramfis, MA, LPC","telephone":"(703) 680-7950","address":"4379 Ridgewood Center Dr #102 Woodbridge, VA 22192","properties1":["Counseling - Board Certified"],"properties2":["American Board of Medical Specialties"],"properties3":[]},{"id":"49210018","name":"Mahboob, Syed K, MBBS","telephone":"(703) 680-7950","address":"4379 Ridgewood Center Dr #102 Woodbridge, VA 22192","properties1":["Family Practice","Geriatric Medicine"],"properties2":["NCQA's Patient-Centered Medical Home Recognition","American Board of Medical Specialties","Evidence Based Medicine Standards"],"properties3":[]},{"id":"46032805","name":"Rodriguez, Jacqueline E, MSW, LCSWR, LCSW","telephone":"(703) 680-7950","address":"4379 Ridgewood Center Dr #102 Woodbridge, VA 22192","properties1":["Social Work - Board Certified"],"properties2":["American Board of Medical Specialties"],"properties3":[]},{"id":"60185738","name":"Mohiuddin, Rashid A, MD","telephone":"(703) 680-7950","address":"4379 Ridgewood Center Dr #102 Woodbridge, VA 22192","properties1":["Family Practice - Board Certified"],"properties2":["NCQA's Patient-Centered Medical Home Recognition","American Board of Medical Specialties","Evidence Based Medicine Standards"],"properties3":[]},{"id":"49851163","name":"Maddock, Laura K, MA, LPC","telephone":"(703) 680-7950","address":"4379 Ridgewood Center Dr #102 Woodbridge, VA 22192","properties1":["Counseling - Board Certified"],"properties2":["American Board of Medical Specialties"],"properties3":[]},{"id":"50007605","name":"Dolby-Mcdonald, Mary, MSW, LCSW","telephone":"(703) 897-8970","address":"4349 Ridgewood Center Dr #101 Woodbridge, VA 22192","properties1":["Social Work"],"properties2":[],"properties3":[]},{"id":"63031851","name":"Band, Stephen Robert R, PHD, LPC, LMFT","telephone":"(703) 680-7950","address":"4379 Ridgewood Center Dr #102 Woodbridge, VA 22192","properties1":["Counseling - Board Certified","Psychology - Board Certified"],"properties2":["American Board of Medical Specialties"],"properties3":[]},{"id":"52815989","name":"Zimomra, Mary S, MA, LPC, LMFT","telephone":"(703) 680-7950","address":"4379 Ridgewood Center Dr #102 Woodbridge, VA 22192","properties1":["Counseling - Board Certified"],"properties2":["American Board of Medical Specialties"],"properties3":[]},{"id":"49890600","name":"Darling, Angela C, DC","telephone":"(571) 432-8001","address":"4310 Ridgewood Center Dr Woodbridge, VA 22192","properties1":["Chiropractic"],"properties2":[],"properties3":[]},{"id":"45925480","name":"Daing, Renato D, MD","telephone":"(703) 680-7950","address":"4379 Ridgewood Center Dr #102 Woodbridge, VA 22192","properties1":["Pediatrics - Board Certified","Adolescent Medicine","Years in Practice: 31"],"properties2":["American Board of Medical Specialties"],"properties3":[]},{"id":"63160422","name":"Salazar, Yorvska M, PSYD, LPC","telephone":"(703) 680-7950","address":"4379 Ridgewood Center Dr #102 Woodbridge, VA 22192","properties1":["Counseling - Board Certified","Psychology - Board Certified"],"properties2":["American Board of Medical Specialties"],"properties3":[]},{"id":"62890691","name":"Zeballos, Ana R, NP, FNP","telephone":"(703) 680-7950","address":"4379 Ridgewood Center Dr #102 Woodbridge, VA 22192","properties1":["Family Nurse Practitioner - Primary Care","Years in Practice: 2"],"properties2":["American Board of Medical Specialties"],"properties3":[]},{"id":"25111058","name":"Ramsey, Harold E, MSN, LNP, APRN","telephone":"(703) 897-8970","address":"4349 Ridgewood Center Dr #101 Woodbridge, VA 22192","properties1":["Behaviorial Nurse - Board Certified","Counseling - Board Certified"],"properties2":["American Board of Medical Specialties"],"properties3":[]},{"id":"35919286","name":"Al-Shammaa, Hussien A, MD","telephone":"(703) 680-7950","address":"4379 Ridgewood Center Dr #102 Woodbridge, VA 22192","properties1":["Pediatrics - Board Certified","Years in Practice: 34"],"properties2":["American Board of Medical Specialties","\n\t\t\t\t\t\t\t\t\t\t\t\t\tNot enough info to evaluate for Evidence Based Medicine Standards.\n\t\t\t\t\t\t\t\t\t\t\t\t"],"properties3":[]},{"id":"24917016","name":"Folks, Jennifer L, NP","telephone":"(703) 680-7950","address":"4379 Ridgewood Center Dr #102 Woodbridge, VA 22192","properties1":["Nurse Practitioner","Years in Practice: 10"],"properties2":[],"properties3":[]},{"id":"37325360","name":"Kotopoulos, Katie, FNP","telephone":"(703) 680-7950","address":"4379 Ridgewood Center Dr #102 Woodbridge, VA 22192","properties1":["Family Nurse Practitioner"],"properties2":["NCQA's Patient-Centered Medical Home Recognition"],"properties3":[]},{"id":"34973461","name":"Linderman, Linnea P, MD","telephone":"(703) 680-7950","address":"4379 Ridgewood Center Dr #102 Woodbridge, VA 22192","properties1":["Pediatrics - Board Certified","Years in Practice: 33"],"properties2":["American Board of Medical Specialties"],"properties3":[]},{"id":"37920662","name":"Fannin, Maureen V, MSW, LCSW","telephone":"(703) 626-0381","address":"4300 Ridgewood Center Dr #A Woodbridge, VA 22192","properties1":["Social Work"],"properties2":[],"properties3":[]},{"id":"21333572","name":"Sonnenbrot, Gissel A, FNP","telephone":"(703) 680-7950","address":"4379 Ridgewood Center Dr #102 Woodbridge, VA 22192","properties1":["Family Nurse Practitioner - Primary Care","Years in Practice: 1"],"properties2":["American Board of Medical Specialties"],"properties3":[]},{"id":"32461258","name":"Dayton, Zaida I, MS, LPC","telephone":"(703) 680-7950","address":"4379 Ridgewood Center Dr #102 Woodbridge, VA 22192","properties1":["Counseling - Board Certified"],"properties2":["American Board of Medical Specialties"],"properties3":[]},{"id":"39433429","name":"Carroll, Sarah J, MS, LMFT","telephone":"(703) 680-7950","address":"4379 Ridgewood Center Dr #102 Woodbridge, VA 22192","properties1":["Counseling"],"properties2":[],"properties3":[]},{"id":"40626519","name":"McCleary, Carol S, PSYD, CP","telephone":"(703) 495-3164","address":"4310 Ridgewood Center Dr Woodbridge, VA 22192","properties1":["Psychology"],"properties2":[],"properties3":[]},{"id":"32819339","name":"Constant, Jean Andre, MSW, LCSW","telephone":"(703) 680-7950","address":"4379 Ridgewood Center Dr #102 Woodbridge, VA 22192","properties1":["Social Work - Board Certified"],"properties2":["American Board of Medical Specialties"],"properties3":[]},{"id":"20625762","name":"Henegan Cohen, Hilary, MSW, LCSW","telephone":"(703) 283-0680","address":"4300 Ridgewood Center Dr #A Woodbridge, VA 22192","properties1":["Social Work"],"properties2":[],"properties3":[]},{"id":"33776550","name":"Jimenez-Tosado, Zahir Z, MD","telephone":"(703) 680-7950","address":"4379 Ridgewood Center Dr #102 Woodbridge, VA 22192","properties1":["Family Practice - Board Certified"],"properties2":["NCQA's Patient-Centered Medical Home Recognition","American Board of Medical Specialties","Evidence Based Medicine Standards"],"properties3":[]},{"id":"36969943","name":"Cozzens, Dennis T, MD","telephone":"(703) 897-8970","address":"4349 Ridgewood Center Dr #101 Woodbridge, VA 22192","properties1":["Psychiatry - Board Certified"],"properties2":["American Board of Medical Specialties"],"properties3":[]},{"id":"27068184","name":"Kunzig, Thomas J, MSW, LCSW","telephone":"(703) 897-8970","address":"4349 Ridgewood Center Dr #101 Woodbridge, VA 22192","properties1":["Social Work"],"properties2":[],"properties3":[]},{"id":"22047430","name":"Carr, Kimberly J, MSW, LCSW","telephone":"(703) 897-8970","address":"4349 Ridgewood Center Dr #101 Woodbridge, VA 22192","properties1":["Social Work - Board Certified"],"properties2":["American Board of Medical Specialties"],"properties3":[]},{"id":"42383261","name":"Greater Prince William Area Community Health Center","telephone":"(703) 680-7950","address":"4379 Ridgewood Center Dr #102 Woodbridge, VA 22192","properties1":["Emergency Medicine"],"properties2":[],"properties3":[]},{"id":"52243684","name":"Daher, Ramsey J, MD","telephone":"(703) 580-0181","address":"14010 Smoketown Rd #117 Woodbridge, VA 22192","properties1":["Internal Medicine - Board Certified","Gastroenterology","Years in Practice: 7"],"properties2":["American Board of Medical Specialties"],"properties3":[]},{"id":"58931708","name":"Marathe, Atul V, MD","telephone":"(703) 580-0181","address":"14010 Smoketown Rd #117 Woodbridge, VA 22192","properties1":["Gastroenterology - Board Certified","Years in Practice: 21"],"properties2":["American Board of Medical Specialties","\n\t\t\t\t\t\t\t\t\t\t\t\t\tNot enough info to evaluate for Evidence Based Medicine Standards.\n\t\t\t\t\t\t\t\t\t\t\t\t"],"properties3":[]},{"id":"60284382","name":"Vamadevan, Arunan S, MD","telephone":"(703) 580-0181","address":"14010 Smoketown Rd #117 Woodbridge, VA 22192","properties1":["Gastroenterology - Board Certified"],"properties2":["American Board of Medical Specialties","\n\t\t\t\t\t\t\t\t\t\t\t\t\tNot enough info to evaluate for Evidence Based Medicine Standards.\n\t\t\t\t\t\t\t\t\t\t\t\t"],"properties3":[]},{"id":"56822182","name":"Brown, Michael W, MD","telephone":"(703) 580-0181","address":"14010 Smoketown Rd #117 Woodbridge, VA 22192","properties1":["Urology - Board Certified","Years in Practice: 35"],"properties2":["American Board of Medical Specialties","Evidence Based Medicine Standards"],"properties3":[]},{"id":"62844944","name":"Huang, Jack C, MD","telephone":"(703) 580-0181","address":"14010 Smoketown Rd #117 Woodbridge, VA 22192","properties1":["Gastroenterology - Board Certified","Years in Practice: 19"],"properties2":["American Board of Medical Specialties","\n\t\t\t\t\t\t\t\t\t\t\t\t\tNot enough info to evaluate for Evidence Based Medicine Standards.\n\t\t\t\t\t\t\t\t\t\t\t\t"],"properties3":[]},{"id":"61074688","name":"Kazemi, Ali F, MD","telephone":"(703) 580-0181","address":"14010 Smoketown Rd #117 Woodbridge, VA 22192","properties1":["Internal Medicine - Board Certified","Gastroenterology","Years in Practice: 8"],"properties2":["American Board of Medical Specialties","\n\t\t\t\t\t\t\t\t\t\t\t\t\tNot enough info to evaluate for Evidence Based Medicine Standards.\n\t\t\t\t\t\t\t\t\t\t\t\t"],"properties3":[]},{"id":"54779752","name":"Procaccino, Frank M, MD","telephone":"(703) 580-0181","address":"14010 Smoketown Rd #117 Woodbridge, VA 22192","properties1":["Gastroenterology - Board Certified","Years in Practice: 30"],"properties2":["American Board of Medical Specialties","\n\t\t\t\t\t\t\t\t\t\t\t\t\tNot enough info to evaluate for Evidence Based Medicine Standards.\n\t\t\t\t\t\t\t\t\t\t\t\t"],"properties3":[]},{"id":"61285872","name":"Wilson, Nicholas J, MD","telephone":"(703) 580-0181","address":"14010 Smoketown Rd #117 Woodbridge, VA 22192","properties1":["Gastroenterology - Board Certified","Years in Practice: 7"],"properties2":["American Board of Medical Specialties"],"properties3":[]},{"id":"61021750","name":"Polley, Tina, FNP","telephone":"(703) 580-0181","address":"14010 Smoketown Rd #117 Woodbridge, VA 22192","properties1":["Family Nurse Practitioner","Years in Practice: 3"],"properties2":[],"properties3":[]},{"id":"28428310","name":"Aram, Ghazaleh, MD","telephone":"(703) 580-0181","address":"14010 Smoketown Rd #117 Woodbridge, VA 22192","properties1":["Gastroenterology - Board Certified","Years in Practice: 15"],"properties2":["American Board of Medical Specialties","\n\t\t\t\t\t\t\t\t\t\t\t\t\tNot enough info to evaluate for Evidence Based Medicine Standards.\n\t\t\t\t\t\t\t\t\t\t\t\t"],"properties3":[]},{"id":"23265133","name":"Josovitz, Kenneth N, MD","telephone":"(703) 580-0181","address":"14010 Smoketown Rd #117 Woodbridge, VA 22192","properties1":["Gastroenterology - Board Certified","Years in Practice: 26"],"properties2":["American Board of Medical Specialties","\n\t\t\t\t\t\t\t\t\t\t\t\t\tNot enough info to evaluate for Evidence Based Medicine Standards.\n\t\t\t\t\t\t\t\t\t\t\t\t"],"properties3":[]},{"id":"27617489","name":"Brown, Michael C, MD","telephone":"(703) 580-0181","address":"14010 Smoketown Rd #117 Woodbridge, VA 22192","properties1":["Gastroenterology - Board Certified","Years in Practice: 24"],"properties2":["American Board of Medical Specialties","\n\t\t\t\t\t\t\t\t\t\t\t\t\tNot enough info to evaluate for Evidence Based Medicine Standards.\n\t\t\t\t\t\t\t\t\t\t\t\t"],"properties3":[]},{"id":"25165062","name":"Thadani, Anisha R, MD","telephone":"(703) 580-0181","address":"14010 Smoketown Rd #117 Woodbridge, VA 22192","properties1":["Gastroenterology - Board Certified","Years in Practice: 12"],"properties2":["American Board of Medical Specialties","\n\t\t\t\t\t\t\t\t\t\t\t\t\tNot enough info to evaluate for Evidence Based Medicine Standards.\n\t\t\t\t\t\t\t\t\t\t\t\t"],"properties3":[]},{"id":"31082770","name":"Young, Benjamin E II, MD","telephone":"(703) 580-0181","address":"14010 Smoketown Rd #117 Woodbridge, VA 22192","properties1":["Gastroenterology - Board Certified","Internal Medicine - Board Certified","Years in Practice: 11"],"properties2":["American Board of Medical Specialties","\n\t\t\t\t\t\t\t\t\t\t\t\t\tNot enough info to evaluate for Evidence Based Medicine Standards.\n\t\t\t\t\t\t\t\t\t\t\t\t"],"properties3":[]},{"id":"40502484","name":"Endoscopy Assoc LLC","telephone":"(703) 580-0180","address":"14010 Smoketown Rd #117 Woodbridge, VA 22192","properties1":["Gastroenterology"],"properties2":[],"properties3":[]},{"id":"41423446","name":"Associates in Gastroenterology PC","telephone":"(703) 580-0181","address":"14010 Smoketown Rd #117 Woodbridge, VA 22192","properties1":["Gastroenterology","Internal Medicine"],"properties2":[],"properties3":[]},{"id":"52862878","name":"Bennett, Elizabeth A, MD, DPM","telephone":"(703) 878-8800","address":"4167 Merchant Plz Lake Ridge, VA 22192","properties1":["Family Practice - Board Certified","Years in Practice: 22"],"properties2":["American Board of Medical Specialties"],"properties3":[]},{"id":"68741908","name":"Duke, Christopher J, MD","telephone":"(703) 878-8800","address":"4167 Merchant Plz Woodbridge, VA 22192","properties1":["Internal Medicine - Board Certified","Years in Practice: 29"],"properties2":["American Board of Medical Specialties"],"properties3":[]},{"id":"69015346","name":"Wierzbicki, John J, DO","telephone":"(703) 878-8800","address":"4167 Merchant Plz Woodbridge, VA 22192","properties1":["Family Practice - Board Certified","Years in Practice: 15"],"properties2":["American Board of Medical Specialties"],"properties3":[]},{"id":"68462435","name":"Sedrakyan, Gevorg, MD","telephone":"(703) 878-8800","address":"4167 Merchant Plz Woodbridge, VA 22192","properties1":["Family Practice - Board Certified","Internal Medicine - Board Certified","Years in Practice: 13"],"properties2":["American Board of Medical Specialties"],"properties3":[]},{"id":"69559238","name":"Black, Jerrold G, MD","telephone":"(703) 878-8800","address":"4167 Merchant Plz Woodbridge, VA 22192","properties1":["Family Practice - Board Certified","Years in Practice: 39"],"properties2":["American Board of Medical Specialties"],"properties3":[]},{"id":"68173616","name":"Mennen, Barnett G, MD","telephone":"(703) 878-8800","address":"4167 Merchant Plz Woodbridge, VA 22192","properties1":["Family Practice","Years in Practice: 46"],"properties2":["American Board of Medical Specialties","\n\t\t\t\t\t\t\t\t\t\t\t\t\tNot enough info to evaluate for Evidence Based Medicine Standards.\n\t\t\t\t\t\t\t\t\t\t\t\t"],"properties3":[]},{"id":"69329743","name":"Robinette, Laura E, MD","telephone":"(707) 878-8800","address":"4167 Merchant Plz Woodbridge, VA 22192","properties1":["Internal Medicine - Board Certified","Pediatrics - Board Certified","Years in Practice: 11"],"properties2":["American Board of Medical Specialties","Evidence Based Medicine Standards"],"properties3":[]},{"id":"69283526","name":"Murthy, Priya, MD","telephone":"(703) 878-8800","address":"4167 Merchant Plz Woodbridge, VA 22192","properties1":["Family Practice - Board Certified"],"properties2":["American Board of Medical Specialties"],"properties3":[]},{"id":"51452340","name":"Bock, Joanna M, MD","telephone":"(703) 878-8800","address":"4167 Merchant Plz Woodbridge, VA 22192","properties1":["Internal Medicine - Board Certified","Family Practice","Years in Practice: 11"],"properties2":["NCQA's Patient-Centered Medical Home Recognition","American Board of Medical Specialties","Evidence Based Medicine Standards"],"properties3":[]},{"id":"59821348","name":"Pervaiz, Sabeen, MD","telephone":"(703) 878-8800","address":"4167 Merchant Plaza Dr Woodbridge, VA 22192","properties1":["Family Practice - Board Certified","Years in Practice: 10"],"properties2":["American Board of Medical Specialties"],"properties3":[]},{"id":"58563676","name":"Allen Winslow, Erica M, MD","telephone":"(703) 878-8800","address":"4167 Merchant Plz Woodbridge, VA 22192","properties1":["Family Practice - Board Certified","Years in Practice: 15"],"properties2":["American Board of Medical Specialties","Evidence Based Medicine Standards"],"properties3":[]},{"id":"60434622","name":"Fleurancois, Nancy, MD","telephone":"(703) 878-8800","address":"4167 Merchant Plz Woodbridge, VA 22192","properties1":["Internal Medicine - Board Certified","Years in Practice: 11"],"properties2":["American Board of Medical Specialties"],"properties3":[]},{"id":"50577420","name":"Borodatcheva, Maria V, MD","telephone":"(703) 878-8800","address":"4167 Merchant Plz Woodbridge, VA 22192","properties1":["Internal Medicine - Board Certified","Years in Practice: 18"],"properties2":["American Board of Medical Specialties","Evidence Based Medicine Standards"],"properties3":[]},{"id":"20013354","name":"Marco, Sam, MD","telephone":"(707) 878-8800","address":"4167 Merchant Plz Woodbridge, VA 22192","properties1":["Family Practice - Board Certified","Years in Practice: 25"],"properties2":["American Board of Medical Specialties"],"properties3":[]},{"id":"23519977","name":"Loveless, Joel E, DO","telephone":"(703) 878-8800","address":"4167 Merchant Plz Woodbridge, VA 22192","properties1":["Family Practice - Board Certified","Years in Practice: 19"],"properties2":["American Board of Medical Specialties"],"properties3":[]},{"id":"30246285","name":"Kim, Elisabeth K, OD","telephone":"(703) 878-8818","address":"4160 Merchant Plz Woodbridge, VA 22192","properties1":["Optometry","Years in Practice: 25"],"properties2":[],"properties3":[]},{"id":"30255163","name":"Major, Makeyshia K, MSW, LCSW","telephone":"(703) 497-1771","address":"4004 Genesee Pl #101 Woodbridge, VA 22192","properties1":["Social Work - Board Certified"],"properties2":["American Board of Medical Specialties"],"properties3":[]},{"id":"37257426","name":"Brown, Amaris, MC, LPC","telephone":"(703) 495-3164","address":"4004 Genesee Pl #101 Woodbridge, VA 22192","properties1":["Counseling - Board Certified"],"properties2":["American Board of Medical Specialties"],"properties3":[]},{"id":"50641608","name":"Cook, Lesley C, PSYD, LCP","telephone":"(540) 845-6940","address":"4000 Genesee Pl #109 Woodbridge, VA 22192","properties1":["Psychology - Board Certified"],"properties2":["American Board of Medical Specialties"],"properties3":[]},{"id":"46842773","name":"Czajka, Anna T, MD","telephone":"(855) 739-9953","address":"4004 Genesee Pl #105 Woodbridge, VA 22192","properties1":["Cardiovascular Disease - Board Certified","Internal Medicine - Board Certified","Years in Practice: 17"],"properties2":["American Board of Medical Specialties","Evidence Based Medicine Standards"],"properties3":[]},{"id":"44099560","name":"Hoagland, Claire A, MSW, LCSW","telephone":"(703) 583-7504","address":"4000 Genesee Pl #109 Woodbridge, VA 22192","properties1":["Social Work - Board Certified"],"properties2":["American Board of Medical Specialties"],"properties3":[]},{"id":"61415954","name":"Root, Cara M, MS, LCSW","telephone":"(540) 845-6940","address":"4000 Genesee Pl #109 Woodbridge, VA 22192","properties1":["Social Work - Board Certified","Counseling"],"properties2":["American Board of Medical Specialties"],"properties3":[]},{"id":"52321579","name":"Faught, Beverly J, MSW, LCSW","telephone":"(540) 845-6940","address":"4000 Genesee Pl #109 Woodbridge, VA 22192","properties1":["Social Work - Board Certified"],"properties2":["American Board of Medical Specialties"],"properties3":[]},{"id":"30892809","name":"Thau, Kenneth R, MSW, LCSWC","telephone":"(540) 845-6940","address":"4000 Genesee Pl #109 Woodbridge, VA 22192","properties1":["Social Work - Board Certified"],"properties2":["American Board of Medical Specialties"],"properties3":[]},{"id":"22649877","name":"Kline, Erin W, DC","telephone":"(703) 680-4344","address":"4004 Genesee Pl #213 Woodbridge, VA 22192","properties1":["Chiropractic - Board Certified"],"properties2":["American Board of Medical Specialties"],"properties3":[]},{"id":"31161796","name":"Gillespie, Corliss D, MS, LPC","telephone":"(571) 402-2509","address":"4000 Genesee Pl #109 Woodbridge, VA 22192","properties1":["Counseling - Board Certified"],"properties2":["American Board of Medical Specialties"],"properties3":[]},{"id":"21524752","name":"Berenji, Kambeez, MD","telephone":"(855) 739-9953","address":"4004 Genesee Pl #515 Woodbridge, VA 22192","properties1":["Cardiology, Interventional - Board Certified","Cardiovascular Disease - Board Certified","Surgery, Vascular","Years in Practice: 26"],"properties2":["American Board of Medical Specialties","\n\t\t\t\t\t\t\t\t\t\t\t\t\tNot enough info to evaluate for Evidence Based Medicine Standards.\n\t\t\t\t\t\t\t\t\t\t\t\t"],"properties3":[]},{"id":"64113640","name":"Magnus Heart &amp; Vascular, Inc","telephone":"(855) 739-9953","address":"4004 Genesee Pl #105 Woodbridge, VA 22192","properties1":["Internal Medicine"],"properties2":[],"properties3":[]},{"id":"40344890","name":"Vista Heart &amp; Vascular PLLC","telephone":"(855) 739-9953","address":"4004 Genesee Pl #105 Woodbridge, VA 22192","properties1":["Cardiovascular Disease","Internal Medicine"],"properties2":[],"properties3":[]},{"id":"41364442","name":"Heart &amp; Vascular Institute of Virginia, Inc","telephone":"(855) 739-9953","address":"4004 Genesee Pl #105 Woodbridge, VA 22192","properties1":["Cardiovascular Disease"],"properties2":[],"properties3":[]},{"id":"51481092","name":"Sauve, William M, MD","telephone":"(703) 915-7076","address":"13625 Office Pl #101 Woodbridge, VA 22192","properties1":["Psychiatry - Board Certified"],"properties2":["American Board of Medical Specialties"],"properties3":[]},{"id":"55151878","name":"Graves, Betty O, MSW, LCSW","telephone":"(703) 670-5738","address":"13649 Office Pl #102 Woodbridge, VA 22192","properties1":["Social Work - Board Certified"],"properties2":["American Board of Medical Specialties"],"properties3":[]},{"id":"52917300","name":"Harlan, Katherine B, PHD, LP, LCP, CPC","telephone":"(703) 670-5738","address":"13649 Office Pl #102 Woodbridge, VA 22192","properties1":["Psychology - Board Certified"],"properties2":["American Board of Medical Specialties"],"properties3":[]},{"id":"59437306","name":"Bowmer, Sam, MSW, LCSW","telephone":"(703) 670-5738","address":"13649 Office Pl #102 Woodbridge, VA 22192","properties1":["Social Work - Board Certified"],"properties2":["American Board of Medical Specialties"],"properties3":[]},{"id":"54128823","name":"Cheatham, Latoya D, MSW, LCSW","telephone":"(703) 670-5738","address":"13649 Office Pl #102 Woodbridge, VA 22192","properties1":["Social Work - Board Certified"],"properties2":["American Board of Medical Specialties"],"properties3":[]},{"id":"35280393","name":"Galdo, Kathleen C, MSW, LICSW, LCSW","telephone":"(703) 670-5738","address":"13649 Office Pl #102 Woodbridge, VA 22192","properties1":["Social Work"],"properties2":[],"properties3":[]},{"id":"24818742","name":"Copp, Danica, MSW, LCSW","telephone":"(703) 670-5738","address":"13649 Office Pl #102 Woodbridge, VA 22192","properties1":["Social Work - Board Certified"],"properties2":["American Board of Medical Specialties"],"properties3":[]},{"id":"53590661","name":"Lane, Kenyona, MSW, LCSW","telephone":"(703) 653-0650","address":"3095 Ps Business Center Dr Woodbridge, VA 22192","properties1":["Social Work - Board Certified"],"properties2":["American Board of Medical Specialties"],"properties3":[]},{"id":"46886069","name":"Owusu-Nyamekye, Nana A, MD","telephone":"(571) 542-4950","address":"4500 Pond Way #170 Woodbridge, VA 22192","properties1":["Internal Medicine","Years in Practice: 6"],"properties2":["NCQA's Patient-Centered Medical Home Recognition","American Board of Medical Specialties","Evidence Based Medicine Standards"],"properties3":[]},{"id":"55195016","name":"Patel, Milan R, DO","telephone":"(571) 542-4950","address":"4500 Pond Way #170 Woodbridge, VA 22192","properties1":["Family Practice - Board Certified","Years in Practice: 18"],"properties2":["NCQA's Patient-Centered Medical Home Recognition","American Board of Medical Specialties","Evidence Based Medicine Standards"],"properties3":[]},{"id":"45736122","name":"Williams, Raenell C, MD","telephone":"(571) 542-4950","address":"4500 Pond Way #170 Woodbridge, VA 22192","properties1":["Family Practice - Board Certified","Years in Practice: 14"],"properties2":["NCQA's Patient-Centered Medical Home Recognition","American Board of Medical Specialties","Evidence Based Medicine Standards"],"properties3":[]},{"id":"19884909","name":"Sales, Benedict B, MD","telephone":"(571) 542-4950","address":"4500 Pond Way #170 Woodbridge, VA 22192","properties1":["Family Practice - Board Certified","Years in Practice: 12"],"properties2":["NCQA's Patient-Centered Medical Home Recognition","American Board of Medical Specialties","Evidence Based Medicine Standards"],"properties3":[]},{"id":"64772091","name":"Dominion Family Health, PLC","telephone":"(571) 542-4950","address":"4500 Pond Way #170 Woodbridge, VA 22192","properties1":["Family Practice"],"properties2":[],"properties3":[]},{"id":"40909498","name":"Currituck Internal Medicine &amp; General Practice","telephone":"(571) 542-4950","address":"4500 Pond Way #170 Woodbridge, VA 22192","properties1":["Family Practice"],"properties2":[],"properties3":[]},{"id":"68363019","name":"Rolley, Ashley J, PT","telephone":"(571) 659-2612","address":"12731 Marblestone Dr #202 Woodbridge, VA 22192","properties1":["Physical Therapy","Years in Practice: 5"],"properties2":[],"properties3":[]},{"id":"68228021","name":"Schrader, Lisa M, MS, BCBA","telephone":"(571) 589-0201","address":"12731 Marblestone Dr #101 Woodbridge, VA 22192","properties1":["Counseling - Board Certified"],"properties2":["American Board of Medical Specialties"],"properties3":[]},{"id":"69194267","name":"Watkins, Stephanie, MA, BCABA","telephone":"(571) 589-0201","address":"12731 Marblestone Dr #101 Woodbridge, VA 22192","properties1":["Counseling - Board Certified"],"properties2":["American Board of Medical Specialties"],"properties3":[]},{"id":"52380491","name":"Bartolozzi, Mark A, MD","telephone":"(703) 730-4848","address":"12701 Marblestone Dr #130 Woodbridge, VA 22192","properties1":["Surgery, General - Board Certified","Years in Practice: 25"],"properties2":["American Board of Medical Specialties"],"properties3":[]},{"id":"49468524","name":"Dila, Darrell D, DPT","telephone":"(571) 659-2612","address":"12731 Marblestone Dr #202 Woodbridge, VA 22192","properties1":["Physical Therapy","Years in Practice: 2"],"properties2":[],"properties3":[]},{"id":"50314839","name":"Alemzadeh, Amir, MD","telephone":"(703) 897-4700","address":"12731 Marblestone Dr #200 Woodbridge, VA 22192","properties1":["Internal Medicine - Board Certified","Years in Practice: 19"],"properties2":["American Board of Medical Specialties","Evidence Based Medicine Standards"],"properties3":[]},{"id":"50420761","name":"Horton-Thompson, Camille E, MD","telephone":"(703) 368-3161","address":"12701 Marblestone Dr #130 Woodbridge, VA 22192","properties1":["Family Practice - Board Certified"],"properties2":["American Board of Medical Specialties","Evidence Based Medicine Standards"],"properties3":[]},{"id":"58007171","name":"Gordon, Matthew R, PT","telephone":"(579) 659-2612","address":"12731 Marblestone Dr #202 Woodbridge, VA 22192","properties1":["Physical Therapy - Board Certified"],"properties2":["American Board of Medical Specialties"],"properties3":[]},{"id":"53754657","name":"Hashemi, Ali R, MD","telephone":"(571) 316-2345","address":"12731 Marblestone Dr #200 Woodbridge, VA 22192","properties1":["Orthopedic Surgery - Board Certified","Surgery, Hand","Years in Practice: 14"],"properties2":["American Board of Medical Specialties","\n\t\t\t\t\t\t\t\t\t\t\t\t\tNot enough info to evaluate for Evidence Based Medicine Standards.\n\t\t\t\t\t\t\t\t\t\t\t\t"],"properties3":[]},{"id":"27921524","name":"Zijerdi, David A, MD","telephone":"(571) 316-2345","address":"12731 Marblestone Dr #200 Woodbridge, VA 22192","properties1":["Orthopedic Surgery - Board Certified","Years in Practice: 14"],"properties2":["American Board of Medical Specialties","\n\t\t\t\t\t\t\t\t\t\t\t\t\tNot enough info to evaluate for Evidence Based Medicine Standards.\n\t\t\t\t\t\t\t\t\t\t\t\t"],"properties3":[]},{"id":"26949332","name":"Greetham, Christopher J, PT","telephone":"(571) 659-2612","address":"12731 Marblestone Dr #202 Woodbridge, VA 22192","properties1":["Physical Therapy - Board Certified"],"properties2":["American Board of Medical Specialties"],"properties3":[]},{"id":"27134068","name":"Magalski, Joseph J Jr., MD","telephone":"(571) 284-4350","address":"12701 Marblestone Dr #130 Woodbridge, VA 22192","properties1":["Surgery, General - Board Certified","Years in Practice: 23"],"properties2":["American Board of Medical Specialties"],"properties3":[]},{"id":"20025360","name":"Stoner, Travis H, DPT","telephone":"(571) 659-2612","address":"12731 Marblestone Dr #202 Woodbridge, VA 22192","properties1":["Physical Therapy","Years in Practice: 12"],"properties2":[],"properties3":[]},{"id":"23560440","name":"Moussavi, Sohail, MD","telephone":"(703) 897-4700","address":"12731 Marblestone Dr #200 Woodbridge, VA 22192","properties1":["Internal Medicine - Board Certified","Years in Practice: 18"],"properties2":["American Board of Medical Specialties","Evidence Based Medicine Standards"],"properties3":[]},{"id":"23191136","name":"Farough, Atoussa, MD","telephone":"(703) 897-4700","address":"12731 Marblestone Dr #200 Woodbridge, VA 22192","properties1":["Internal Medicine - Board Certified","Years in Practice: 12"],"properties2":["American Board of Medical Specialties","Evidence Based Medicine Standards"],"properties3":[]},{"id":"35854380","name":"Alemzadeh, Nazanin, MD","telephone":"(703) 897-4700","address":"12731 Marblestone Dr #200 Woodbridge, VA 22192","properties1":["Internal Medicine - Board Certified","Years in Practice: 18"],"properties2":["American Board of Medical Specialties","Evidence Based Medicine Standards"],"properties3":[]},{"id":"64907959","name":"Lake Ridge Physical Therapy","telephone":"(571) 659-2612","address":"12731 Marblestone Dr #202 Woodbridge, VA 22192","properties1":["Physical Therapy"],"properties2":[],"properties3":[]},{"id":"47809509","name":"Deright, Jonathan, PHD, CP","telephone":"(703) 680-4200","address":"4320 Prince William Pky #109 Woodbridge, VA 22192","properties1":["Psychology"],"properties2":[],"properties3":[]},{"id":"36537892","name":"Bartlett, Brandie J, PSYD, CP","telephone":"(703) 680-4200","address":"4320 Prince William Pky #109 Woodbridge, VA 22192","properties1":["Psychology - Board Certified"],"properties2":["American Board of Medical Specialties"],"properties3":[]},{"id":"22489806","name":"Fitzgerald, Karen M, PHD, CP","telephone":"(703) 680-4200","address":"4320 Prince William Pky #109 Woodbridge, VA 22192","properties1":["Psychology - Board Certified"],"properties2":["American Board of Medical Specialties"],"properties3":[]},{"id":"69200353","name":"Phan, Christina T, OD","telephone":"(703) 494-6184","address":"14465 Potomac Mills Rd Woodbridge, VA 22192","properties1":["Optometry - Board Certified","Years in Practice: 3"],"properties2":["American Board of Medical Specialties"],"properties3":[]},{"id":"49572032","name":"Patel, Preyaben, OD","telephone":"(703) 494-6184","address":"14465 Potomac Mills Rd Woodbridge, VA 22192","properties1":["Optometry","Years in Practice: 2"],"properties2":[],"properties3":[]},{"id":"43789464","name":"Lee, Jennifer C, OD","telephone":"(703) 494-6184","address":"14465 Potomac Mills Rd Woodbridge, VA 22192","properties1":["Optometry"],"properties2":[],"properties3":[]},{"id":"59266015","name":"Bertomeu, Vincent A, OD","telephone":"(703) 494-6184","address":"14465 Potomac Mills Rd Woodbridge, VA 22192","properties1":["Optometry","Years in Practice: 16"],"properties2":[],"properties3":[]},{"id":"45312049","name":"Spirer, Judith, OD","telephone":"(703) 494-6184","address":"14465 Potomac Mills Rd Woodbridge, VA 22192","properties1":["Optometry","Years in Practice: 14"],"properties2":[],"properties3":[]},{"id":"44768321","name":"Farahmand, Neda, OD","telephone":"(703) 494-6184","address":"14465 Potomac Mills Rd Woodbridge, VA 22192","properties1":["Optometry","Years in Practice: 11"],"properties2":[],"properties3":[]},{"id":"63496172","name":"Stich, Matthew T, MD","telephone":"(703) 494-5200","address":"14465 Potomac Mills Rd Woodbridge, VA 22192","properties1":["Ophthalmology - Board Certified","Years in Practice: 33"],"properties2":["American Board of Medical Specialties","\n\t\t\t\t\t\t\t\t\t\t\t\t\tNot enough info to evaluate for Evidence Based Medicine Standards.\n\t\t\t\t\t\t\t\t\t\t\t\t"],"properties3":[]},{"id":"46646936","name":"Doering, Linda M, OD","telephone":"(703) 494-6184","address":"14465 Potomac Mills Rd Woodbridge, VA 22192","properties1":["Optometry"],"properties2":[],"properties3":[]},{"id":"48140940","name":"Apted, Scott H, OD","telephone":"(703) 494-6184","address":"14465 Potomac Mills Rd Woodbridge, VA 22192","properties1":["Optometry","Years in Practice: 31"],"properties2":[],"properties3":[]},{"id":"44810939","name":"McCarthy, Hjelmgren McCa L, OD","telephone":"(703) 494-6184","address":"14465 Potomac Mills Rd Woodbridge, VA 22192","properties1":["Optometry","Years in Practice: 15"],"properties2":[],"properties3":[]},{"id":"38112169","name":"Haghshenas, Mojgan, OD","telephone":"(703) 494-6184","address":"14465 Potomac Mills Rd Woodbridge, VA 22192","properties1":["Optometry","Years in Practice: 17"],"properties2":[],"properties3":[]},{"id":"21976760","name":"Bui-Platten, Oanh K, OD","telephone":"(703) 494-6184","address":"14465 Potomac Mills Rd Woodbridge, VA 22192","properties1":["Optometry"],"properties2":[],"properties3":[]},{"id":"26292778","name":"Aggarwal, Sara L, OD","telephone":"(703) 494-6184","address":"14465 Potomac Mills Rd Woodbridge, VA 22192","properties1":["Optometry","Years in Practice: 19"],"properties2":[],"properties3":[]},{"id":"28926502","name":"Patel, Kesha, OD","telephone":"(703) 494-6184","address":"14465 Potomac Mills Rd Woodbridge, VA 22192","properties1":["Optometry"],"properties2":[],"properties3":[]},{"id":"26315284","name":"Santos-Delgado, Gabriel, OD","telephone":"(703) 494-6184","address":"14465 Potomac Mills Rd Woodbridge, VA 22192","properties1":["Optometry"],"properties2":[],"properties3":[]},{"id":"23368763","name":"Versteegden, Keith, OD","telephone":"(703) 494-6184","address":"14465 Potomac Mills Rd Woodbridge, VA 22192","properties1":["Optometry","Years in Practice: 2"],"properties2":[],"properties3":[]},{"id":"40625237","name":"Asim, Mehar G, OD","telephone":"(703) 494-6184","address":"14465 Potomac Mills Rd Woodbridge, VA 22192","properties1":["Optometry","Years in Practice: 3"],"properties2":[],"properties3":[]},{"id":"29556067","name":"Kim, Sun H, OD","telephone":"(703) 494-6184","address":"14465 Potomac Mills Rd Woodbridge, VA 22192","properties1":["Optometry"],"properties2":[],"properties3":[]},{"id":"38477160","name":"Harbi, Danah N, OD","telephone":"(703) 494-6184","address":"14465 Potomac Mills Rd Woodbridge, VA 22192","properties1":["Optometry"],"properties2":[],"properties3":[]},{"id":"32776731","name":"Wiley, Susan M, OD","telephone":"(703) 494-6184","address":"14465 Potomac Mills Rd Woodbridge, VA 22192","properties1":["Optometry","Years in Practice: 34"],"properties2":[],"properties3":[]},{"id":"36652095","name":"Zalar, Michael E, OD","telephone":"(703) 494-6184","address":"14465 Potomac Mills Rd Woodbridge, VA 22192","properties1":["Optometry","Years in Practice: 24"],"properties2":[],"properties3":[]},{"id":"23754307","name":"Guerreiro, Rosa, OD","telephone":"(703) 494-6184","address":"14465 Potomac Mills Rd Woodbridge, VA 22192","properties1":["Optometry","Years in Practice: 19"],"properties2":[],"properties3":[]},{"id":"65330511","name":"Northern Virginia Eye Associates PC","telephone":"(703) 494-6184","address":"14465 Potomac Mills Rd Woodbridge, VA 22192","properties1":["Ophthalmology"],"properties2":[],"properties3":[]},{"id":"68458759","name":"Sabharwal, Charu, MD","telephone":"(703) 729-3420","address":"4897 Prince William Pky #102 Woodbridge, VA 22192","properties1":["Internal Medicine - Board Certified","Sleep Medicine - Board Certified","Years in Practice: 23"],"properties2":["American Board of Medical Specialties","\n\t\t\t\t\t\t\t\t\t\t\t\t\tNot enough info to evaluate for Evidence Based Medicine Standards.\n\t\t\t\t\t\t\t\t\t\t\t\t"],"properties3":[]},{"id":"69370209","name":"Shahzeidi, Shahriar S, MD","telephone":"(703) 729-3420","address":"4897 Prince William Pky #C-102 Woodbridge, VA 22192","properties1":["Pediatric Pulmonology - Board Certified","Pediatrics - Board Certified","Sleep Medicine - Board Certified","Years in Practice: 37"],"properties2":["American Board of Medical Specialties"],"properties3":[]},{"id":"47949935","name":"Prasanna, Swarnalatha, MD, LPC, LMFT","telephone":"(703) 492-0500","address":"4893 Prince William Pky #101 Woodbridge, VA 22192","properties1":["Psychiatry - Board Certified"],"properties2":["American Board of Medical Specialties"],"properties3":[]},{"id":"23699623","name":"Rotolo, Sean D, MD","telephone":"(703) 729-3420","address":"4897 Prince William Pky #C 102 Woodbridge, VA 22192","properties1":["Sleep Medicine - Board Certified","Years in Practice: 8"],"properties2":["American Board of Medical Specialties","\n\t\t\t\t\t\t\t\t\t\t\t\t\tNot enough info to evaluate for Evidence Based Medicine Standards.\n\t\t\t\t\t\t\t\t\t\t\t\t"],"properties3":[]},{"id":"45900319","name":"Delgado, Karla, MA, LPC","telephone":"(703) 396-7215","address":"2501 Hunter Pl #201 Woodbridge, VA 22192","properties1":["Counseling - Board Certified"],"properties2":["American Board of Medical Specialties"],"properties3":[]},{"id":"40029452","name":"Koshes, Ronald J, MD","telephone":"(703) 659-9863","address":"2501 Hunter Pl #201 Woodbridge, VA 22192","properties1":["Psychiatry - Board Certified"],"properties2":["American Board of Medical Specialties"],"properties3":[]},{"id":"24833105","name":"Decardi, Adlin Maria M, MA, LMFT","telephone":"(703) 396-7215","address":"2501 Hunter Pl #201 Woodbridge, VA 22192","properties1":["Counseling - Board Certified"],"properties2":["American Board of Medical Specialties"],"properties3":[]},{"id":"46264687","name":"Derosa, Gary A, MD","telephone":"(703) 368-3161","address":"14000 Worth Ave Woodbridge, VA 22192","properties1":["Family Practice - Board Certified","Years in Practice: 38"],"properties2":["NCQA's Heart Stroke Recognition","NCQA's Diabetes Recognition","NCQA's Patient-Centered Medical Home Recognition","American Board of Medical Specialties"],"properties3":[]},{"id":"24404122","name":"Kim, Joo H, OD","telephone":"(703) 497-2777","address":"14000 Worth Ave #13996 Woodbridge, VA 22192","properties1":["Optometry","Years in Practice: 12"],"properties2":[],"properties3":[]},{"id":"61777510","name":"Steer, Hugh C, OD","telephone":"(703) 490-5275","address":"2700 Potomac Mills Cir Woodbridge, VA 22192","properties1":["Optometry"],"properties2":[],"properties3":[]},{"id":"68439093","name":"Harshberger, Christy M, MSN","telephone":"(910) 528-0517","address":"14330 Gideon Dr Woodbridge, VA 22192","properties1":["Nurse Practitioner","Years in Practice: 7"],"properties2":[],"properties3":[]},{"id":"36677639","name":"Alexander, Mary A, MD","telephone":"(910) 528-0517","address":"14330 Gideon Dr Woodbridge, VA 22192","properties1":["Internal Medicine - Board Certified","Years in Practice: 20"],"properties2":["American Board of Medical Specialties","\n\t\t\t\t\t\t\t\t\t\t\t\t\tNot enough info to evaluate for Evidence Based Medicine Standards.\n\t\t\t\t\t\t\t\t\t\t\t\t"],"properties3":[]},{"id":"65919221","name":"Cavery Wellness of Woodbridge LLC","telephone":"(910) 528-0517","address":"14330 Gideon Dr Woodbridge, VA 22192","properties1":["Family Practice"],"properties2":[],"properties3":[]},{"id":"56087852","name":"Chan, Douglas K, PT","telephone":"(703) 730-6400","address":"3767 Fettler Park Dr Dumfries, VA 22025","properties1":["Physical Therapy","Years in Practice: 24"],"properties2":[],"properties3":[]},{"id":"63151047","name":"Vertudes, Christian, DPT","telephone":"(703) 730-6400","address":"3767 Fettler Park Dr Dumfries, VA 22025","properties1":["Physical Therapy - Board Certified","Years in Practice: 3"],"properties2":["American Board of Medical Specialties"],"properties3":[]},{"id":"19909723","name":"Zhao, Chi G, MD","telephone":"(703) 729-3420","address":"3687 Fettler Park Dr Dumfries, VA 22025","properties1":["Sleep Medicine - Board Certified","Years in Practice: 11"],"properties2":["American Board of Medical Specialties","\n\t\t\t\t\t\t\t\t\t\t\t\t\tNot enough info to evaluate for Evidence Based Medicine Standards.\n\t\t\t\t\t\t\t\t\t\t\t\t"],"properties3":[]},{"id":"22915234","name":"Fatema, Kaniz, MD","telephone":"(571) 499-5813","address":"3990 Fettler Park Dr #B Dumfries, VA 22025","properties1":["Family Practice - Board Certified","Years in Practice: 29"],"properties2":["American Board of Medical Specialties"],"properties3":[]},{"id":"64797851","name":"Professional Physical Therapy LLC","telephone":"(703) 730-6400","address":"3767 Fettler Park Dr Dumfries, VA 22025","properties1":["Physical Therapy - Board Certified"],"properties2":["American Board of Medical Specialties"],"properties3":[]},{"id":"64788535","name":"Nextcare Urgent Care","telephone":"(571) 499-5813","address":"3990 Fettler Park Dr #B Dumfries, VA 22025","properties1":["Family Practice"],"properties2":[],"properties3":[]},{"id":"68817330","name":"Coates, Joseph B, MD","telephone":"(703) 897-5890","address":"12581 Milstead Way #103 Woodbridge, VA 22192","properties1":["Family Practice - Board Certified"],"properties2":["American Board of Medical Specialties","\n\t\t\t\t\t\t\t\t\t\t\t\t\tNot enough info to evaluate for Evidence Based Medicine Standards.\n\t\t\t\t\t\t\t\t\t\t\t\t"],"properties3":[]},{"id":"69582267","name":"Virginia Urgent Care LLC","telephone":"(703) 897-5890","address":"12581 Milstead Way #103 Woodbridge, VA 22192","properties1":["Family Practice"],"properties2":[],"properties3":[]},{"id":"58429774","name":"Khiri, Eman H, MD","telephone":"(703) 897-5890","address":"12581 Milstead Way #103 Woodbridge, VA 22192","properties1":["Family Practice - Board Certified","Years in Practice: 15"],"properties2":["American Board of Medical Specialties"],"properties3":[]},{"id":"56837324","name":"Campbell, Michelle M, MD","telephone":"(540) 368-5603","address":"12581 Milstead Way #103 Woodbridge, VA 22192","properties1":["Family Practice - Board Certified","Years in Practice: 16"],"properties2":["American Board of Medical Specialties"],"properties3":[]},{"id":"61666145","name":"Breen, Jacqueline M, DO","telephone":"(703) 897-5890","address":"12581 Milstead Way #103 Woodbridge, VA 22192","properties1":["Family Practice - Board Certified","Years in Practice: 27"],"properties2":["American Board of Medical Specialties"],"properties3":[]},{"id":"57318902","name":"Tedesco, Mark J, MD","telephone":"(703) 897-5890","address":"12581 Milstead Way #103 Woodbridge, VA 22192","properties1":["Family Practice - Board Certified","Years in Practice: 31"],"properties2":["American Board of Medical Specialties"],"properties3":[]},{"id":"41042298","name":"Bradshaw, Donald M, MD","telephone":"(703) 897-5890","address":"12581 Milstead Way #103 Woodbridge, VA 22192","properties1":["Family Practice - Board Certified","Years in Practice: 36"],"properties2":["American Board of Medical Specialties"],"properties3":[]},{"id":"38180232","name":"Mbanu, Ibeawuchi O, MD","telephone":"(703) 897-5890","address":"12581 Milstead Way #103 Woodbridge, VA 22192","properties1":["Internal Medicine - Board Certified","Years in Practice: 16","Internal Medicine - Board Certified","Years in Practice: 16"],"properties2":["American Board of Medical Specialties","Evidence Based Medicine Standards","American Board of Medical Specialties","Evidence Based Medicine Standards"],"properties3":[]},{"id":"47469404","name":"Shin, Paul R, MD","telephone":"(703) 680-1770","address":"13580 Groupe Dr #105 Woodbridge, VA 22192","properties1":["Urology - Board Certified","Years in Practice: 20","Urology - Board Certified","Years in Practice: 20"],"properties2":["American Board of Medical Specialties","Evidence Based Medicine Standards","American Board of Medical Specialties","Evidence Based Medicine Standards"],"properties3":[]},{"id":"48494253","name":"Malik, Shruti, MD","telephone":"(703) 680-1770","address":"13580 Groupe Dr #105 Woodbridge, VA 22192","properties1":["Reproductive Endocrinology/Infertility","Years in Practice: 10","Reproductive Endocrinology/Infertility","Years in Practice: 10"],"properties2":[],"properties3":[]},{"id":"50581304","name":"Mirkhel, Ahmadshah S, MD","telephone":"(703) 961-0488","address":"2751 Killarney Dr Woodbridge, VA 22192","properties1":["Internal Medicine - Board Certified","Nephrology - Board Certified","Years in Practice: 14","Internal Medicine - Board Certified","Nephrology - Board Certified","Years in Practice: 14"],"properties2":["American Board of Medical Specialties","\n\t\t\t\t\t\t\t\t\t\t\t\t\tNot enough info to evaluate for Evidence Based Medicine Standards.\n\t\t\t\t\t\t\t\t\t\t\t\t","American Board of Medical Specialties","\n\t\t\t\t\t\t\t\t\t\t\t\t\tNot enough info to evaluate for Evidence Based Medicine Standards.\n\t\t\t\t\t\t\t\t\t\t\t\t"],"properties3":[]},{"id":"57910071","name":"Tandra, Neeraja, MBBS","telephone":"(703) 961-0488","address":"2751 Killarney Dr Woodbridge, VA 22192","properties1":["Nephrology - Board Certified","Nephrology - Board Certified"],"properties2":["American Board of Medical Specialties","American Board of Medical Specialties"],"properties3":[]},{"id":"60113417","name":"Al Baqui, Nowal, MD","telephone":"(703) 961-0488","address":"2751 Killarney Dr Woodbridge, VA 22192","properties1":["Nephrology","Years in Practice: 8","Nephrology","Years in Practice: 8"],"properties2":[],"properties3":[]},{"id":"52645312","name":"Zaheer, Misbah, MBBS","telephone":"(703) 961-0488","address":"2751 Killarney Dr Woodbridge, VA 22192","properties1":["Nephrology - Board Certified","Years in Practice: 13","Nephrology - Board Certified","Years in Practice: 13"],"properties2":["American Board of Medical Specialties","\n\t\t\t\t\t\t\t\t\t\t\t\t\tNot enough info to evaluate for Evidence Based Medicine Standards.\n\t\t\t\t\t\t\t\t\t\t\t\t","American Board of Medical Specialties","\n\t\t\t\t\t\t\t\t\t\t\t\t\tNot enough info to evaluate for Evidence Based Medicine Standards.\n\t\t\t\t\t\t\t\t\t\t\t\t"],"properties3":[]},{"id":"61729154","name":"Mahoney, David L, MD","telephone":"(703) 961-0488","address":"2751 Killarney Dr Woodbridge, VA 22192","properties1":["Nephrology - Board Certified","Internal Medicine","Years in Practice: 32","Nephrology - Board Certified","Internal Medicine","Years in Practice: 32"],"properties2":["American Board of Medical Specialties","American Board of Medical Specialties"],"properties3":[]},{"id":"33019783","name":"Musio, Franco, MD","telephone":"(703) 961-0488","address":"2751 Killarney Dr Woodbridge, VA 22192","properties1":["Nephrology - Board Certified","Years in Practice: 32","Nephrology - Board Certified","Years in Practice: 32"],"properties2":["American Board of Medical Specialties","American Board of Medical Specialties"],"properties3":[]},{"id":"65372545","name":"Nephrology Associates of Northern Virginia, Inc","telephone":"(703) 961-0480","address":"2751 Killarney Dr Woodbridge, VA 22192","properties1":["Nephrology","Nephrology"],"properties2":[],"properties3":[]},{"id":"38180232","name":"Mbanu, Ibeawuchi O, MD","telephone":"(703) 897-5890","address":"12581 Milstead Way #103 Woodbridge, VA 22192","properties1":["Internal Medicine - Board Certified","Years in Practice: 16","Internal Medicine - Board Certified","Years in Practice: 16"],"properties2":["American Board of Medical Specialties","Evidence Based Medicine Standards","American Board of Medical Specialties","Evidence Based Medicine Standards"],"properties3":[]},{"id":"47469404","name":"Shin, Paul R, MD","telephone":"(703) 680-1770","address":"13580 Groupe Dr #105 Woodbridge, VA 22192","properties1":["Urology - Board Certified","Years in Practice: 20","Urology - Board Certified","Years in Practice: 20"],"properties2":["American Board of Medical Specialties","Evidence Based Medicine Standards","American Board of Medical Specialties","Evidence Based Medicine Standards"],"properties3":[]},{"id":"48494253","name":"Malik, Shruti, MD","telephone":"(703) 680-1770","address":"13580 Groupe Dr #105 Woodbridge, VA 22192","properties1":["Reproductive Endocrinology/Infertility","Years in Practice: 10","Reproductive Endocrinology/Infertility","Years in Practice: 10"],"properties2":[],"properties3":[]},{"id":"50581304","name":"Mirkhel, Ahmadshah S, MD","telephone":"(703) 961-0488","address":"2751 Killarney Dr Woodbridge, VA 22192","properties1":["Internal Medicine - Board Certified","Nephrology - Board Certified","Years in Practice: 14","Internal Medicine - Board Certified","Nephrology - Board Certified","Years in Practice: 14"],"properties2":["American Board of Medical Specialties","\n\t\t\t\t\t\t\t\t\t\t\t\t\tNot enough info to evaluate for Evidence Based Medicine Standards.\n\t\t\t\t\t\t\t\t\t\t\t\t","American Board of Medical Specialties","\n\t\t\t\t\t\t\t\t\t\t\t\t\tNot enough info to evaluate for Evidence Based Medicine Standards.\n\t\t\t\t\t\t\t\t\t\t\t\t"],"properties3":[]},{"id":"57910071","name":"Tandra, Neeraja, MBBS","telephone":"(703) 961-0488","address":"2751 Killarney Dr Woodbridge, VA 22192","properties1":["Nephrology - Board Certified","Nephrology - Board Certified"],"properties2":["American Board of Medical Specialties","American Board of Medical Specialties"],"properties3":[]},{"id":"60113417","name":"Al Baqui, Nowal, MD","telephone":"(703) 961-0488","address":"2751 Killarney Dr Woodbridge, VA 22192","properties1":["Nephrology","Years in Practice: 8","Nephrology","Years in Practice: 8"],"properties2":[],"properties3":[]},{"id":"52645312","name":"Zaheer, Misbah, MBBS","telephone":"(703) 961-0488","address":"2751 Killarney Dr Woodbridge, VA 22192","properties1":["Nephrology - Board Certified","Years in Practice: 13","Nephrology - Board Certified","Years in Practice: 13"],"properties2":["American Board of Medical Specialties","\n\t\t\t\t\t\t\t\t\t\t\t\t\tNot enough info to evaluate for Evidence Based Medicine Standards.\n\t\t\t\t\t\t\t\t\t\t\t\t","American Board of Medical Specialties","\n\t\t\t\t\t\t\t\t\t\t\t\t\tNot enough info to evaluate for Evidence Based Medicine Standards.\n\t\t\t\t\t\t\t\t\t\t\t\t"],"properties3":[]},{"id":"61729154","name":"Mahoney, David L, MD","telephone":"(703) 961-0488","address":"2751 Killarney Dr Woodbridge, VA 22192","properties1":["Nephrology - Board Certified","Internal Medicine","Years in Practice: 32","Nephrology - Board Certified","Internal Medicine","Years in Practice: 32"],"properties2":["American Board of Medical Specialties","American Board of Medical Specialties"],"properties3":[]},{"id":"33019783","name":"Musio, Franco, MD","telephone":"(703) 961-0488","address":"2751 Killarney Dr Woodbridge, VA 22192","properties1":["Nephrology - Board Certified","Years in Practice: 32","Nephrology - Board Certified","Years in Practice: 32"],"properties2":["American Board of Medical Specialties","American Board of Medical Specialties"],"properties3":[]},{"id":"65372545","name":"Nephrology Associates of Northern Virginia, Inc","telephone":"(703) 961-0480","address":"2751 Killarney Dr Woodbridge, VA 22192","properties1":["Nephrology","Nephrology"],"properties2":[],"properties3":[]}]
