[{"id":"62035246","name":"Mellion, Aminah S, MSW, LCSW","telephone":"(703) 746-3600","address":"2355A Mill Rd Alexandria, VA 22314","properties1":["Social Work - Board Certified"],"properties2":["American Board of Medical Specialties"],"properties3":[]},{"id":"32018429","name":"Ince, Tamara, MS, LICSW","telephone":"(240) 292-9322","address":"2331 Mill Rd #100 Alexandria, VA 22314","properties1":["Counseling - Board Certified","Social Work - Board Certified"],"properties2":["American Board of Medical Specialties"],"properties3":[]},{"id":"72134985","name":"Mehra, Rhea N, MD","telephone":"(703) 774-3234","address":"2121 Eisenhower Ave #200 Alexandria, VA 22314","properties1":["Psychiatry - Board Certified"],"properties2":["American Board of Medical Specialties"],"properties3":[]},{"id":"30464932","name":"Haas, Christine H, LD","telephone":"(703) 552-2722","address":"2121 Eisenhower Ave #200 Alexandria, VA 22314","properties1":["Nutrition","Years in Practice: 15"],"properties2":[],"properties3":[]},{"id":"65385156","name":"NU Weights LLC","telephone":"(703) 552-2722","address":"2121 Eisenhower Ave #200 Alexandria, VA 22314","properties1":["Nutrition"],"properties2":[],"properties3":[]},{"id":"41099667","name":"Dietetic Consultants of Northern VA LLC","telephone":"(703) 519-0901","address":"2121 Eisenhower Ave #200 Alexandria, VA 22314","properties1":["Nutrition"],"properties2":[],"properties3":[]},{"id":"38837941","name":"Eason, Athalia, MS, LPC","telephone":"(540) 656-3662","address":"1940 Duke St #200 Alexandria, VA 22314","properties1":["Counseling - Board Certified"],"properties2":["American Board of Medical Specialties"],"properties3":[]},{"id":"73628049","name":"Thomas, Peter R, MD","telephone":"(703) 810-5209","address":"2805 Duke St Alexandria, VA 22314","properties1":["Orthopedic Surgery - Board Certified","Years in Practice: 12"],"properties2":["American Board of Medical Specialties","\n\t\t\t\t\t\t\t\t\t\t\t\t\tNot enough info to evaluate for Evidence Based Medicine Standards.\n\t\t\t\t\t\t\t\t\t\t\t\t"],"properties3":[]},{"id":"73700557","name":"Kittredge, Ben W IV, MD","telephone":"(703) 810-5209","address":"2805 Duke St Alexandria, VA 22314","properties1":["Orthopedic Surgery - Board Certified","Years in Practice: 19"],"properties2":["American Board of Medical Specialties","\n\t\t\t\t\t\t\t\t\t\t\t\t\tNot enough info to evaluate for Evidence Based Medicine Standards.\n\t\t\t\t\t\t\t\t\t\t\t\t"],"properties3":[]},{"id":"73483132","name":"Weingold, Daniel E, MD","telephone":"(703) 810-5209","address":"2805 Duke St Alexandria, VA 22314","properties1":["Orthopedic Surgery - Board Certified","Years in Practice: 26"],"properties2":["American Board of Medical Specialties","\n\t\t\t\t\t\t\t\t\t\t\t\t\tNot enough info to evaluate for Evidence Based Medicine Standards.\n\t\t\t\t\t\t\t\t\t\t\t\t"],"properties3":[]},{"id":"73065594","name":"Martinelli, Thomas A, MD","telephone":"(703) 810-5209","address":"2805 Duke St Alexandria, VA 22314","properties1":["Orthopedic Surgery - Board Certified","Years in Practice: 32"],"properties2":["American Board of Medical Specialties","\n\t\t\t\t\t\t\t\t\t\t\t\t\tNot enough info to evaluate for Evidence Based Medicine Standards.\n\t\t\t\t\t\t\t\t\t\t\t\t"],"properties3":[]},{"id":"72393537","name":"Hughes, Steven S, MD","telephone":"(703) 810-5209","address":"2805 Duke St Alexandria, VA 22314","properties1":["Orthopedic Surgery - Board Certified","Years in Practice: 32"],"properties2":["American Board of Medical Specialties","\n\t\t\t\t\t\t\t\t\t\t\t\t\tNot enough info to evaluate for Evidence Based Medicine Standards.\n\t\t\t\t\t\t\t\t\t\t\t\t"],"properties3":[]},{"id":"45099243","name":"You, Young J, MD","telephone":"(703) 810-5209","address":"2805 Duke St Alexandria, VA 22314","properties1":["Orthopedic Surgery - Board Certified","Years in Practice: 43"],"properties2":["American Board of Medical Specialties","\n\t\t\t\t\t\t\t\t\t\t\t\t\tNot enough info to evaluate for Evidence Based Medicine Standards.\n\t\t\t\t\t\t\t\t\t\t\t\t"],"properties3":[]},{"id":"40869426","name":"Gynecare Associates","telephone":"(703) 461-7000","address":"2807 Duke St Alexandria, VA 22314","properties1":["Obstetrics and Gynecology"],"properties2":[],"properties3":[]},{"id":"47627354","name":"Cho, Che B, LAC","telephone":"(703) 370-2830","address":"2819 Duke St Alexandria, VA 22314","properties1":["Acupuncture","Years in Practice: 16"],"properties2":[],"properties3":[]},{"id":"27641988","name":"Khouri Popp, Lorena S, MD","telephone":"(703) 751-4702","address":"2839 Duke St Alexandria, VA 22314","properties1":["Internal Medicine - Board Certified","Years in Practice: 16"],"properties2":["American Board of Medical Specialties","Evidence Based Medicine Standards"],"properties3":[]},{"id":"31861204","name":"Fruiterman, Jan P, MD","telephone":"(703) 751-4702","address":"2839 Duke St Alexandria, VA 22314","properties1":["Obstetrics and Gynecology - Board Certified","Years in Practice: 45"],"properties2":["American Board of Medical Specialties"],"properties3":[]},{"id":"44763681","name":"Lin, Steven H, DPM","telephone":"(703) 823-2357","address":"2843 Duke St Alexandria, VA 22314","properties1":["Podiatry","Years in Practice: 22"],"properties2":[],"properties3":[]},{"id":"56957474","name":"Lee, Richard G, DPM","telephone":"(703) 823-2357","address":"2843 Duke St Alexandria, VA 22314","properties1":["Podiatry","Years in Practice: 21"],"properties2":[],"properties3":[]},{"id":"28792209","name":"Arjomandi, Neda, DPM","telephone":"(703) 823-2357","address":"2843 Duke St Alexandria, VA 22314","properties1":["Podiatry","Years in Practice: 8"],"properties2":[],"properties3":[]},{"id":"44058224","name":"De Sumrak, Nocolette, PSYD, CP","telephone":"(571) 721-1085","address":"2851 Duke St #13 Alexandria, VA 22314","properties1":["Psychology - Board Certified"],"properties2":["American Board of Medical Specialties"],"properties3":[]},{"id":"47118562","name":"Ansari, Zafar A, MD","telephone":"(301) 396-4800","address":"2849 Duke St #14 Alexandria, VA 22314","properties1":["Internal Medicine - Board Certified","Years in Practice: 21"],"properties2":["American Board of Medical Specialties"],"properties3":[]},{"id":"31562663","name":"Rentie, Rashika J, PHD, CP","telephone":"(571) 721-1085","address":"2851 Duke St #13 Alexandria, VA 22314","properties1":["Psychology - Board Certified"],"properties2":["American Board of Medical Specialties"],"properties3":[]},{"id":"61302599","name":"Premier Eye Center LLC","telephone":"(703) 751-4040","address":"2849 Duke St Alexandria, VA 22314","properties1":["Ophthalmology"],"properties2":[],"properties3":[]},{"id":"26306404","name":"Buxo, Francisco J, MD","telephone":"(703) 751-7880","address":"2853 Duke St Bldg #3 Alexandria, VA 22314","properties1":["Obstetrics and Gynecology","Years in Practice: 33"],"properties2":["American Board of Medical Specialties","Evidence Based Medicine Standards"],"properties3":[]},{"id":"58139917","name":"Myaing, Alfred C, MD","telephone":"(703) 823-0720","address":"2863 Duke St Alexandria, VA 22314","properties1":["Cardiovascular Disease"],"properties2":["\n\t\t\t\t\t\t\t\t\t\t\t\t\tNot enough info to evaluate for Evidence Based Medicine Standards.\n\t\t\t\t\t\t\t\t\t\t\t\t"],"properties3":[]},{"id":"52938589","name":"Aria, Nancy N, MD","telephone":"(703) 461-7500","address":"2865 Duke St Bldg 3 Alexandria, VA 22314","properties1":["Dermatology - Board Certified","Years in Practice: 19"],"properties2":["American Board of Medical Specialties","\n\t\t\t\t\t\t\t\t\t\t\t\t\tNot enough info to evaluate for Evidence Based Medicine Standards.\n\t\t\t\t\t\t\t\t\t\t\t\t"],"properties3":[]},{"id":"48787190","name":"Aria, James J, MD","telephone":"(703) 461-7500","address":"2865 Duke St Bldg 3 Alexandria, VA 22314","properties1":["Obstetrics and Gynecology - Board Certified","Years in Practice: 49"],"properties2":["American Board of Medical Specialties"],"properties3":[]},{"id":"65577247","name":"James J. Aria PC","telephone":"(703) 461-7500","address":"2865 Duke St Alexandria, VA 22314","properties1":["Obstetrics and Gynecology"],"properties2":[],"properties3":[]},{"id":"20836161","name":"Grapin, Fern L, MD","telephone":"(703) 751-3031","address":"2871 Duke St Bldg 1 Alexandria, VA 22314","properties1":["Obstetrics and Gynecology - Board Certified","Years in Practice: 34"],"properties2":["American Board of Medical Specialties","Evidence Based Medicine Standards"],"properties3":[]},{"id":"40653847","name":"Fern L Grapin PC","telephone":"(703) 751-3031","address":"2871 Duke St Alexandria, VA 22314","properties1":["Obstetrics and Gynecology"],"properties2":[],"properties3":[]},{"id":"31292348","name":"Wallis, Denise D, MD","telephone":"(703) 845-2815","address":"3610 Kings St #D Alexandria, VA 22302","properties1":["Family Practice - Board Certified","Years in Practice: 19"],"properties2":["American Board of Medical Specialties"],"properties3":[]},{"id":"72220876","name":"Neighborhood Health","telephone":"(703) 535-5568","address":"720 N St. Asaph St Alexandria, VA 22314","properties1":["Internal Medicine"],"properties2":[],"properties3":[]},{"id":"44799646","name":"Osborne-Wu, Jewel B, MD","telephone":"(703) 535-5568","address":"720 N St. Asaph St Alexandria, VA 22314","properties1":["Family Practice - Board Certified","Years in Practice: 5"],"properties2":["American Board of Medical Specialties"],"properties3":[]},{"id":"38093452","name":"O'Connor, Elizabeth L, MD","telephone":"(703) 535-5568","address":"720 N Asaph St Alexandria, VA 22314","properties1":["Family Practice - Board Certified","Years in Practice: 19"],"properties2":["American Board of Medical Specialties"],"properties3":[]},{"id":"28147094","name":"Morgan, David M, DDS","telephone":"(703) 751-7841","address":"124 S W St #103 Alexandria, VA 22314","properties1":["Surgery, Oral And Maxillofacial","Years in Practice: 13"],"properties2":[],"properties3":[]},{"id":"59902636","name":"Michener, Frank E, MD","telephone":"(703) 960-4901","address":"2059 Huntington Ave #108 Alexandria, VA 22303","properties1":["Psychiatry - Board Certified"],"properties2":["American Board of Medical Specialties"],"properties3":[]},{"id":"53993471","name":"Chapman, A. . B, MD","telephone":"(703) 960-4901","address":"2059 Huntington Ave #108 Alexandria, VA 22303","properties1":["Psychiatry - Board Certified"],"properties2":["American Board of Medical Specialties"],"properties3":[]},{"id":"49512465","name":"Kelly, Tina V, OD","telephone":"(703) 813-8997","address":"3223 Duke St #B3 Alexandria, VA 22314","properties1":["Optometry"],"properties2":[],"properties3":[]},{"id":"20379790","name":"Reynolds-Temple, Cynthia L, MD, OD","telephone":"(703) 813-8997","address":"3223 Duke St #B3 Alexandria, VA 22314","properties1":["Optometry","Years in Practice: 26"],"properties2":[],"properties3":[]},{"id":"65387721","name":"Nova Eye Care","telephone":"(703) 813-8997","address":"3223 Duke St #B3 Alexandria, VA 22314","properties1":["Optometry"],"properties2":[],"properties3":[]},{"id":"60597102","name":"Kasun, Regina J, NP","telephone":"(703) 836-8838","address":"2729 King St Alexandria, VA 22302","properties1":["Nurse Practitioner","Years in Practice: 8"],"properties2":["\n\t\t\t\t\t\t\t\t\t\t\t\t\tNot enough info to evaluate for Evidence Based Medicine Standards.\n\t\t\t\t\t\t\t\t\t\t\t\t"],"properties3":[]},{"id":"58884395","name":"Bruno, John A Jr., MD","telephone":"(703) 317-2800","address":"5845 Richmond Hwy #400 Alexandria, VA 22303","properties1":["Orthopedic Surgery - Board Certified","Years in Practice: 51"],"properties2":["American Board of Medical Specialties","\n\t\t\t\t\t\t\t\t\t\t\t\t\tNot enough info to evaluate for Evidence Based Medicine Standards.\n\t\t\t\t\t\t\t\t\t\t\t\t"],"properties3":[]},{"id":"41103584","name":"Orthopedic Medicine of Alexandria, Ltd","telephone":"(703) 317-2800","address":"5845 Richmond Hwy #400 Alexandria, VA 22303","properties1":["Orthopedic Surgery"],"properties2":[],"properties3":[]},{"id":"53269146","name":"Fisher, Lashawn, MA, LPC","telephone":"(571) 312-7608","address":"30 S Quaker Ln #210 Alexandria, VA 22314","properties1":["Counseling - Board Certified"],"properties2":["American Board of Medical Specialties"],"properties3":[]},{"id":"61255675","name":"Richard D. Nemeth PLLC","telephone":"(703) 317-9500","address":"5946 Richmond Hwy Alexandria, VA 22303","properties1":["Family Practice"],"properties2":[],"properties3":[]},{"id":"56587012","name":"Adewale, Benjamin A, MD","telephone":"(703) 569-8028","address":"25 S Quaker Ln #35 Alexandria, VA 22314","properties1":["Psychiatry - Board Certified"],"properties2":["American Board of Medical Specialties"],"properties3":[]},{"id":"45218315","name":"Udoh, Eteakamba J, MD","telephone":"(703) 370-1110","address":"20 S Quaker Ln #220 Alexandria, VA 22314","properties1":["Obstetrics and Gynecology - Board Certified","Years in Practice: 9"],"properties2":["American Board of Medical Specialties"],"properties3":[]},{"id":"54350214","name":"York, Daniel C, PSYD, LP, CPC, CP","telephone":"(301) 258-2717","address":"1105 Vassar Rd Alexandria, VA 22314","properties1":["Psychology"],"properties2":[],"properties3":[]},{"id":"53482166","name":"Speed, Jennifer S, MA, LPC, LCPC","telephone":"(703) 754-0636","address":"3307 Duke St Alexandria, VA 22314","properties1":["Counseling - Board Certified"],"properties2":["American Board of Medical Specialties"],"properties3":[]},{"id":"37207972","name":"Brevis, Daniela, MED, LPC","telephone":"(571) 348-3707","address":"3309 Duke St Alexandria, VA 22314","properties1":["Counseling - Board Certified","Counseling - Board Certified"],"properties2":["American Board of Medical Specialties","American Board of Medical Specialties"],"properties3":[]},{"id":"37207972","name":"Brevis, Daniela, MED, LPC","telephone":"(571) 348-3707","address":"3309 Duke St Alexandria, VA 22314","properties1":["Counseling - Board Certified","Counseling - Board Certified"],"properties2":["American Board of Medical Specialties","American Board of Medical Specialties"],"properties3":[]}]
