[{"id":"24943819","name":"Alexander, Myrna B, MA, LPC, DED","telephone":"(703) 979-5159","address":"3850 9th Rd S Arlington, VA 22204","properties1":["Counseling - Board Certified","Social Work - Board Certified"],"properties2":["American Board of Medical Specialties"],"properties3":[]},{"id":"36825817","name":"Kroll, Gloria J, MA, LPC","telephone":"(703) 407-9105","address":"3801 7th St S Arlington, VA 22204","properties1":["Counseling - Board Certified"],"properties2":["American Board of Medical Specialties"],"properties3":[]},{"id":"72926922","name":"Lai, Victoria, MD","telephone":"(703) 717-4250","address":"1625 N George Mason Dr #334 Arlington, VA 22204","properties1":["Surgery, General - Board Certified","Years in Practice: 9"],"properties2":["American Board of Medical Specialties","Evidence Based Medicine Standards"],"properties3":[]},{"id":"24778919","name":"Zinn, Edward, MD","telephone":"(703) 524-6942","address":"333 S Glebe Rd #104 Arlington, VA 22204","properties1":["Psychiatry - Board Certified"],"properties2":["American Board of Medical Specialties"],"properties3":[]},{"id":"49888770","name":"Young, Susan, MS, LPC, LCSW","telephone":"(301) 332-0870","address":"620 S Buchanan St Arlington, VA 22204","properties1":["Counseling","Social Work"],"properties2":[],"properties3":[]},{"id":"51065039","name":"Ziegler, Louis J III, DC","telephone":"(703) 521-0644","address":"46 S Glebe Rd #100 Arlington, VA 22204","properties1":["Chiropractic - Board Certified","Years in Practice: 28"],"properties2":["American Board of Medical Specialties"],"properties3":[]},{"id":"20902984","name":"Lee, Michelle M, LAC","telephone":"(703) 521-0644","address":"46 S Glebe Rd #100 Arlington, VA 22204","properties1":["Acupuncture"],"properties2":[],"properties3":[]},{"id":"38449241","name":"Shafai, Mandana, MD","telephone":"(703) 521-0644","address":"46 S Glebe Rd #100 Arlington, VA 22204","properties1":["Internal Medicine - Board Certified","Years in Practice: 29"],"properties2":["American Board of Medical Specialties","Evidence Based Medicine Standards"],"properties3":[]},{"id":"61057181","name":"Internal Medicine of Arlington PC","telephone":"(703) 521-0644","address":"46 S Glebe Rd #100 Arlington, VA 22204","properties1":["Internal Medicine"],"properties2":[],"properties3":[]},{"id":"36097250","name":"Bird, Sally F, MSW, LCSW","telephone":"(703) 271-8529","address":"404 S Garfield St Arlington, VA 22204","properties1":["Social Work - Board Certified"],"properties2":["American Board of Medical Specialties"],"properties3":[]},{"id":"62731874","name":"Pelletier, Joseph M, LPC, LMFT, EDD, CSAC","telephone":"(703) 271-0287","address":"2300 9th St S #M1 Arlington, VA 22204","properties1":["Psychology - Board Certified","Counseling","Psychology - Board Certified","Counseling"],"properties2":["American Board of Medical Specialties","American Board of Medical Specialties"],"properties3":[]},{"id":"62731874","name":"Pelletier, Joseph M, LPC, LMFT, EDD, CSAC","telephone":"(703) 271-0287","address":"2300 9th St S #M1 Arlington, VA 22204","properties1":["Psychology - Board Certified","Counseling","Psychology - Board Certified","Counseling"],"properties2":["American Board of Medical Specialties","American Board of Medical Specialties"],"properties3":[]}]
